Workbook

Sheet ⓪ 表说明与全链路血缘
A1: doc 19 · 各表「业务含义与全链路血缘」总览（自动生成自 outputs/fcl_table_meta.json）
A2: 表(num) | B2: 层 | C2: 业务含义/目的 | D2: 何时来查 | E2: 为什么这样处理 | F2: 数据粒度 | G2: 上游链路 | H2: 全部上游表 | I2: 下游链路 | J2: 全部下游表 | K2: 备注
A3: ② newrez.portnewrezfc | B3: L1 源（Newrez FCL 主源） | C3: Newrez 每日推送的法拍(FCL)主源表——一笔贷款一行最新快照，含 FCL 时间线里程碑(setup/referral/firstlegal/judgment/sale)、当前阶段 fcstage、4 个 Hold 槽(fchold1..4)、拍卖金额、律师等。 Newrez 法拍全流程的原始事实底座；下游所有 FCL 计算的源头。 | D3: 想看某贷款 Newrez 原始报的 FCL 里程碑/阶段/Hold 原值，或核对下游计算是否忠实于源时。 | E3: 各 Servicer 文件格式不同，先按‘一家一张原始表’落地保真，再到 L4 统一改名/UNION，便于回溯与对账。 | F3: 1 行/贷款/dataasof（每日快照）；本 dump 取 dataasof=MAX。 | G3: Servicer 文件(S3, L0) → newrez.portnewrezfc 〔load_daily_newrez_flow.py；落库 daily_task.py:923-942(MySQL)/960-983(Redshift)〕 | H3: Servicer 文件(S3, L0) | I3: portnewrezfc → tempfc.temp_basic_data_fcl(改名) → port.basic_data_loan_fcl(全 servicer UNION，FCL 事实表) → { port.basic_data_loan_foreclosure〔GEN_FCL_DETAIL basic_data_pool_config.py:253-305〕 / port.fcl_stage_info〔GEN_FCL_STAGE :1774-2440〕 / port.basic_data_loan_foreclosure_hold〔Hold 拆槽 :466-768〕 } → bpms.sync_*〔asset_managment_config.py〕 → bpms.biz_data_view_loan_details_foreclosure(视图) → BPS 法拍面板 | J3: tempfc.temp_basic_data_fcl、port.basic_data_loan_fcl、port.basic_data_loan_foreclosure、port.fcl_stage_info、port.basic_data_loan_foreclosure_hold、bpms.sync_loan_foreclosure、bpms.sync_fcl_stage_info、bpms.sync_loan_foreclosure_hold、bpms.biz_data_view_loan_details_foreclosure
A4: ③ newrez.portnewrezbk | B4: L1 源（Newrez 破产源） | C4: Newrez 破产(BK)源表，按贷款×破产申请记录，含 bkstatus/bkchapter/bkfileddate 等编码字段。 BK 事实底座；为 FCL 提供‘是否在破产保护(暂停法拍)’的判断。 | D4: 查某贷款原始破产章节/状态/申请日，或核对 BPS 破产面板。 | E4: 破产是法拍的暂停因素，需单列保真；编码值经 datadic 解码成业务文案。 | F4: 1 行/贷款/破产申请(bkfileddate)；多次申请多行。 | G4: Servicer 文件(S3, L0) → newrez.portnewrezbk | H4: Servicer 文件(S3, L0) | I4: portnewrezbk → port.basic_data_loan_foreclosure_bankruptcy〔解码 bkstatus，basic_data_pool_config.py:331-370，JOIN newrez.portnewrezdatadic〕 → bpms.sync_loan_foreclosure_bankruptcy〔asset_managment_config.py:822-843〕 → bpms.biz_data_view_loan_details_foreclosure(视图) → BPS 破产面板 | J4: port.basic_data_loan_foreclosure_bankruptcy、bpms.sync_loan_foreclosure_bankruptcy、bpms.biz_data_view_loan_details_foreclosure
A5: ④ newrez.portnewrezlm | B5: L1 源（Newrez 损失缓解 LM 源） | C5: Newrez 损失缓解(LM)源表，按贷款×LM 周期(dealstartdate)，含 lmdeal/lmprogram/lmstatus/lmdecision 等编码。 LM 事实底座；提供‘是否在协商还款方案(暂停/替代法拍)’。 | D5: 查某贷款 LM 周期/项目/决定原值，或核对 BPS LM 面板。 | E5: LM 是法拍的替代/暂停路径，需单列保真；编码经 datadic 解码。 | F5: 1 行/贷款/LM 周期(dealstartdate)；多周期多行。 | G5: Servicer 文件(S3, L0) → newrez.portnewrezlm | H5: Servicer 文件(S3, L0) | I5: portnewrezlm → port.basic_data_loan_foreclosure_loss_mitigation〔basic_data_pool_config.py:799-843，JOIN newrez.portnewrezdatadic〕 → bpms.sync_loan_foreclosure_loss_mitigation〔asset_managment_config.py:799-819〕 → bpms.biz_data_view_loan_details_foreclosure(视图) → BPS LM 面板 | J5: port.basic_data_loan_foreclosure_loss_mitigation、bpms.sync_loan_foreclosure_loss_mitigation、bpms.biz_data_view_loan_details_foreclosure
A6: ⑤ newrez.portnewrezgeneral | B6: L1 源（Newrez 通用源） | C6: Newrez 通用源表(125 列)，含 legalstatus、delinquency_status_mba(MBA 逾期分类)、nextduedate 等账户层属性。 逾期(delinquency)支线的源头；提供 delq_status 原值。 | D6: 查某贷款原始逾期分类/法律状态/下次到期日。 | E6: 逾期与 FCL 是两条支线——逾期来自 general 表经 days360 归一，FCL 来自 portnewrezfc 显式标志；二者在 L4 汇合。FCL 码绝不由 days360 推导。 | F6: 1 行/贷款/dataasof。 | G6: Servicer 文件(S3, L0) → newrez.portnewrezgeneral | H6: Servicer 文件(S3, L0) | I6: portnewrezgeneral.delinquency_status_mba → port.portdaily_v2〔portdaily_config.py〕 → port.basic_data_daily_loan_common.delq_status(逾期支线 L2，daily_data_loan_common_config.py) → port.basic_data_daily_loan_common_clean.delinq(L3，daily_data_loan_common_clean_config.py，CASE+days360) → { port.basic_data_fcl_related.delq_status / port.fcl_stage_info.group / port.portmonthbase } → BPS | J6: port.portdaily_v2、port.basic_data_daily_loan_common、port.basic_data_daily_loan_common_clean、port.basic_data_fcl_related、port.fcl_stage_info、port.portmonthbase、bpms.sync_fcl_stage_info
A7: ⑥ newrez.portnewrezprop | B7: L1 源（Newrez 房产源） | C7: Newrez 房产源表(32 列)，含 propertystate(州，定司法/非司法)、LTV、occupancy 等。 提供物业/州属性；州决定 FCL 走司法(judicial)还是非司法路径。 | D7: 查某贷款物业州/LTV/占用情况。 | E7: 司法/非司法影响 FCL 时长与阶段口径，需物业州维度（实测 state 取自 portnewrezprop.propertystate）。 | F7: 1 行/贷款/dataasof。 | G7: Servicer 文件(S3, L0) → newrez.portnewrezprop | H7: Servicer 文件(S3, L0) | I7: portnewrezprop.propertystate → port.basic_data_daily_loan_common(州维度) / port.basic_data_loan_foreclosure(summary_judicial_foreclosure 司法标志) → bpms.sync_loan_foreclosure → BPS | J7: port.basic_data_daily_loan_common、port.basic_data_loan_foreclosure、bpms.sync_loan_foreclosure
A8: ⑦ port.basic_data_loan_fcl | B8: L4 FCL 事实表（Redshift 快照中间） | C8: Redshift FCL 事实表——portnewrezfc 等经改名后 UNION 全 6 家 servicer 的统一列宽表(每贷款最新 dataasof)。 FCL 计算的统一入口；屏蔽各 servicer 列名差异。 | D8: 查‘统一列名后的 FCL 字段值’，或定位某下游字段来自哪根统一列。 | E8: 各家列名不同，先改名(tempfc.temp_basic_data_fcl)再 UNION 成一张统一事实表，下游只面对一套列名。 | F8: 1 行/贷款（每贷款最新 dataasof）。 | G8: Servicer 文件(L0) → newrez.portnewrezfc(+各家对应表) → tempfc.temp_basic_data_fcl(改名) → port.basic_data_loan_fcl〔UNION，basic_data_pool_config.py〕 | H8: Servicer 文件(L0)、newrez.portnewrezfc、(sls/carrington/mrc/fci/selene 对应源表)、tempfc.temp_basic_data_fcl | I8: basic_data_loan_fcl → { port.basic_data_loan_foreclosure〔GEN_FCL_DETAIL :253-305〕 / port.fcl_stage_info〔GEN_FCL_STAGE :1774-2440〕 / port.basic_data_loan_foreclosure_hold〔:466-768〕 / port.basic_data_loan_foreclosure_loss_mitigation〔:799-843〕 / port.basic_data_loan_foreclosure_bankruptcy〔:331-370〕 } → bpms.sync_* → 视图 → BPS | J8: port.basic_data_loan_foreclosure、port.fcl_stage_info、port.basic_data_loan_foreclosure_hold、port.basic_data_loan_foreclosure_loss_mitigation、port.basic_data_loan_foreclosure_bankruptcy、bpms.sync_loan_foreclosure、bpms.sync_fcl_stage_info、bpms.sync_loan_foreclosure_hold、bpms.sync_loan_foreclosure_loss_mitigation、bpms.sync_loan_foreclosure_bankruptcy、bpms.biz_data_view_loan_details_foreclosure
A9: ⑧ port.basic_data_loan_foreclosure | B9: L4 FCL 聚合（时间线，1 行/贷款） | C9: Redshift FCL 聚合表(1 行/贷款)——一笔贷款端到端法拍时间线：各里程碑日期、当前状态(summary_foreclosure_status)、司法标志、在法拍天数(summary_days_in_fcl)。 bpms.sync_loan_foreclosure(BPS 主表)的直接上游；法拍主视图的数据底座。 | D9: 查某贷款法拍‘何时进入各里程碑/当前状态/在法拍多少天/为何退出’。 | E9: 把事实表里散落的里程碑/状态按业务规则(GEN_FCL_DETAIL CASE)收敛成 1 行/贷款的可读时间线；退出原因直接取 servicer 的 fcremovaldesc(无解码表)。 | F9: 1 行/贷款（含在途 + 已结）。 | G9: … → port.basic_data_loan_fcl → port.basic_data_loan_foreclosure〔GEN_FCL_DETAIL basic_data_pool_config.py:253-305；状态 CASE :273；司法 :277-279；在法拍天数 :1628〕 | H9: port.basic_data_loan_fcl、tempfc.temp_basic_data_fcl、newrez.portnewrezfc、Servicer 文件(L0) | I9: basic_data_loan_foreclosure → (Redshift→MySQL 同步 df_db_util.py:665-699 sync_to_mysql / 702-726 update_to_mysql) → bpms.sync_loan_foreclosure〔GEN_FORECLOSURE asset_managment_config.py:535-608；实时天数校正 :597-598〕 → bpms.biz_data_view_loan_details_foreclosure(视图) → BPS Summary/Timeline 面板 | J9: bpms.sync_loan_foreclosure、bpms.biz_data_view_loan_details_foreclosure
A10: ⑨ port.basic_data_fcl_related | B10: L4 FCL 关联/过滤中间表 | C10: FCL 关联属性中间表(14 列)——诉讼标志、清算类型、BK 标志、违约原因、delq_status 等。 给 stage 计算与过滤提供‘关联属性/分组键’(delq_status → stage group)。 | D10: 查某贷款 stage 分组依据、关联诉讼/清算/违约属性。 | E10: stage 计算需把逾期支线的 delq_status 与 FCL 属性合并；单列一张关联表承接，避免主时间线表过宽。 | F10: 1 行/贷款（最新 dataasof）。 | G10: { port.basic_data_loan_fcl(FCL 属性) + port.basic_data_daily_loan_common_clean.delinq(逾期码) } → port.basic_data_fcl_related〔basic_data_pool_config.py〕 | H10: port.basic_data_loan_fcl、port.basic_data_daily_loan_common_clean | I10: basic_data_fcl_related.delq_status → port.fcl_stage_info.group(stage 分组) → bpms.sync_fcl_stage_info → 视图 → BPS Stage 面板 | J10: port.fcl_stage_info、bpms.sync_fcl_stage_info、bpms.biz_data_view_loan_details_foreclosure
A11: ⑩ port.fcl_stage_info | B11: L4 阶段表（Redshift） | C11: Redshift 阶段表(48 列)——把法拍拆成 6 大阶段，每阶段 5 维(开始/天数/扣除 LM-Hold 重叠等)，每贷款最新 fctrdt。 bpms.sync_fcl_stage_info(BPS 聚合 Stage/Timeline)的上游；面板‘各阶段停留天数’的底座。 | D11: 查某贷款‘在每个阶段停留多久、扣除 LM/Hold 后净时长、当前在哪个阶段组’。 | E11: 业务关心‘卡在哪一步多久’；阶段口径复杂(N:N 扣 LM/Hold 重叠)，单列一张表算清，并 JOIN portfunding 取 funding 维。 | F11: 1 行/贷款/fctrdt。 | G11: { port.basic_data_loan_fcl + port.basic_data_fcl_related(delq_status 分组) + port.portfunding(JOIN) } → port.fcl_stage_info〔GEN_FCL_STAGE basic_data_pool_config.py:1774-2440〕 | H11: port.basic_data_loan_fcl、port.basic_data_fcl_related、port.basic_data_daily_loan_common_clean、port.portfunding | I11: fcl_stage_info → bpms.sync_fcl_stage_info〔GET_FCL_STAGE_DATA asset_managment_config.py:925-929，JOIN port.portfunding〕 → 视图 → BPS Stage 面板 | J11: bpms.sync_fcl_stage_info、bpms.biz_data_view_loan_details_foreclosure
A12: ⑪ port.portfunding | B12: L4 维度（融资池） | C12: 融资池表(57 列，1 行/贷款)——funding/deal 标识(fundingid/dealid)与池属性。 作为 JOIN 维度为 FCL 输出补 funding_id/bid_id，并做入库过滤。 | D12: 查某贷款属于哪个融资池/deal，或为何被 sync 过滤进/出。 | E12: BPS 需按 funding/bid 维展示与归集；FCL 表本身不含，运行时 JOIN portfunding 补齐(dealid→bid_id, fundingid→funding_id)。 | F12: 1 行/贷款（当前态）。 | G12: 投资/融资域(非 servicer FCL 文件) → port.portfunding | H12: 投资/融资域来源（非 FCL servicer 文件） | I12: portfunding ⋈ { port.fcl_stage_info / GEN_FORECLOSURE(asset_managment_config.py:535-608) } → bpms.sync_fcl_stage_info / bpms.sync_loan_foreclosure → 视图 → BPS | J12: port.fcl_stage_info、bpms.sync_fcl_stage_info、bpms.sync_loan_foreclosure、bpms.biz_data_view_loan_details_foreclosure
A13: ⑫ port.basic_data_loan_foreclosure_hold | B13: L4 Hold 历史（Redshift 长表） | C13: Redshift Hold 历史(长表，1 行/Hold)——把源表 4 个 Hold 槽(fchold1..4)拆成长格式；Carrington 多 Hold 先排名压进 4 槽。 bpms.sync_loan_foreclosure_hold(BPS Hold 全历史)的上游；支撑‘一笔法拍多个 Hold’。 | D13: 查某贷款全部 Hold 的起止/原因/历史。 | E13: 源表把 Hold 压成 4 个宽槽，业务要全历史，需拆槽(unpivot)成 1 行/Hold；一笔 FCL 多 Hold 是常态(非数据错误)。 | F13: 1 行/贷款/Hold 段。 | G13: newrez.portnewrezfc(fchold1..4) → port.basic_data_loan_fcl → port.basic_data_loan_foreclosure_hold〔拆槽 basic_data_pool_config.py:466-768；Carrington 排名 :504-629〕 | H13: newrez.portnewrezfc、port.basic_data_loan_fcl | I13: → bpms.sync_loan_foreclosure_hold〔GEN_FORECLOSURE_HOLD asset_managment_config.py:847-894〕 → 视图 → BPS Hold 面板 | J13: bpms.sync_loan_foreclosure_hold、bpms.biz_data_view_loan_details_foreclosure
A14: ⑬ port.basic_data_loan_foreclosure_loss_mitigation | B14: L4 LM 历史（Redshift） | C14: Redshift LM 历史(1 行/LM 周期)——按 (loanid, dealstartdate)，datadic 解码 lmdeal/lmprogram/lmstatus/lmdecision。 bpms.sync_loan_foreclosure_loss_mitigation 的上游；支撑‘一笔贷款多 LM 周期’。 | D14: 查某贷款全部 LM 周期/项目/决定(已解码)。 | E14: LM 多周期是常态；编码需经 datadic 解码成业务文案(JOIN key 拼 code+'.0')。 | F14: 1 行/贷款/LM 周期。 | G14: { newrez.portnewrezlm + newrez.portnewrezdatadic } → port.basic_data_loan_fcl 体系 → port.basic_data_loan_foreclosure_loss_mitigation〔basic_data_pool_config.py:799-843〕 | H14: newrez.portnewrezlm、newrez.portnewrezdatadic、port.basic_data_loan_fcl | I14: → bpms.sync_loan_foreclosure_loss_mitigation〔asset_managment_config.py:799-819〕 → 视图 → BPS LM 面板 | J14: bpms.sync_loan_foreclosure_loss_mitigation、bpms.biz_data_view_loan_details_foreclosure
... A16: ⑮ tempfc.temp_basic_data_fcl | B16: L4 改名临时表（Redshift 运行时中间产物） | C16: Redshift 运行时改名临时表(37 列)——把各 servicer 原始列(如 fcreferraldate)改成统一列(referral_start_date)的中间产物。 port.basic_data_loan_fcl 的直接上游；承接‘改名’这一步。 | D16: 排查‘统一列名 ↔ 源列名’映射、定位改名是否正确。 | E16: UNION 前必须先统一列名；单列一张临时表做改名，逻辑清晰、便于调试；运行时产物。 | F16: 1 行/贷款/dataasof。 | G16: newrez.portnewrezfc(各家源) → tempfc.temp_basic_data_fcl〔改名 basic_data_pool_config.py ~:1538-1565〕 | H16: newrez.portnewrezfc、Servicer 文件(L0) | I16: → port.basic_data_loan_fcl(UNION) → FCL 业务族(foreclosure/stage/hold/lm/bk) → bpms.sync_* → BPS | J16: port.basic_data_loan_fcl、port.basic_data_loan_foreclosure、port.fcl_stage_info、port.basic_data_loan_foreclosure_hold、port.basic_data_loan_foreclosure_loss_mitigation、port.basic_data_loan_foreclosure_bankruptcy
A17: ⑯ port.basic_data_daily_loan_common | B17: L2 逾期支线 统一日表（Redshift） | C17: 逾期支线 L2 统一日表(78 列)——全 servicer UNION 后的标准日表，含 delq_status、fcl_flag、lm_flag 等(asofdate)。 逾期/状态归一的统一入口；L3 清洗的上游。 | D17: 查‘统一后的每日逾期/状态原值’、对账各家归一。 | E17: 各家逾期/状态字段名与取值不同，先 UNION 成统一日表；注意 fcl_flag 在此并未真正归一(Newrez/SLS 为 NULL)，真正归一在 L4 FCL 业务族。 | F17: 1 行/贷款/asofdate。 | G17: Servicer 文件(L0) → newrez.portnewrezgeneral(等各家) → port.portdaily_v2〔portdaily_config.py〕 → port.basic_data_daily_loan_common〔daily_data_loan_common_config.py〕 | H17: Servicer 文件(L0)、newrez.portnewrezgeneral、newrez.portnewrezfc、port.portdaily_v2 | I17: → port.basic_data_daily_loan_common_clean(L3) → { port.portmonthbase / port.basic_data_fcl_related.delq_status / port.fcl_stage_info.group } → BPS | J17: port.basic_data_daily_loan_common_clean、port.basic_data_fcl_related、port.fcl_stage_info、port.portmonthbase | K17: fcl_flag 在 L2 未归一（直传，Newrez/SLS NULL）；真正归一在 L4 FCL 业务族。
A18: ⑰ port.basic_data_daily_loan_common_clean | B18: L3 逾期支线 清洗日表（Redshift） | C18: 逾期支线 L3 清洗日表(103 列)——把 delq_status 经 CASE 归一成标准 delinq 码(C/D30/D60/D90/D120P/FCL/REO/P)，并用 days360(nextduedate,fctrdt) 分桶(fctrdt)。 标准逾期码的单一来源；喂 portmonthbase 与 FCL 业务族(stage 分组)。 | D18: 查‘标准化后的逾期码/天数桶口径’、核对 days360 计算。 | E18: 业务要统一的 MBA 逾期码；文本状态(Foreclosure*/REO/Paid*)直接映射，其余按 days360 天数分桶。注意：FCL 码只来自 servicer 显式法拍状态，绝不由 days360 推导。 | F18: 1 行/贷款/fctrdt。 | G18: … → port.basic_data_daily_loan_common → port.basic_data_daily_loan_common_clean〔daily_data_loan_common_clean_config.py，CASE + days360〕 | H18: port.basic_data_daily_loan_common、port.portdaily_v2、newrez.portnewrezgeneral | I18: → { port.portmonthbase / port.basic_data_fcl_related.delq_status / port.fcl_stage_info.group } → BPS。另：旁支 port.basic_data_loan_delinq_clean(含 is_ghost_payoff 等)实测存在，但其生成代码不在 PrefectFlow 仓库(grep 0 命中，开放问题)。 | J18: port.basic_data_fcl_related、port.fcl_stage_info、port.portmonthbase | K18: 旁支 port.basic_data_loan_delinq_clean 生成代码不在仓库（grep 0 命中，开放问题），未列为确定下游。
A19: ⑱ bpms.sync_loan_foreclosure | B19: L5 BPS 直接对接（主表） | C19: BPS 法拍主表(72 列，当前态)——Summary/Timeline/target 主面板的数据源。 BPS 直接对接表；法拍主面板。 | D19: 查 BPS 主面板某字段的落库值、排查面板与 Redshift 是否一致。 | E19: L4 算好后同步到 MySQL 供 BPS 读；采用覆盖更新(coverage upsert)，并对天数做 NY 当日实时校正(+DATEDIFF)。 | F19: 1 行/贷款（过滤 timeline_referred… IS NOT NULL，即已进入法拍）。 | G19: … → port.basic_data_loan_foreclosure(Redshift) → (sync_to_mysql/update_to_mysql df_db_util.py:665-726) → bpms.sync_loan_foreclosure〔GEN_FORECLOSURE asset_managment_config.py:535-608〕（JOIN port.portfunding 取 funding_id/bid_id） | H19: port.basic_data_loan_foreclosure、port.portfunding、port.basic_data_loan_fcl | I19: → bpms.biz_data_view_loan_details_foreclosure(视图) → BPS 法拍详情/主面板 | J19: bpms.biz_data_view_loan_details_foreclosure | K19: 样例 Loan5(纯 Chapter 13 BK，未进法拍)不在本表，故本 dump 命中 4/5。
A20: ⑲ bpms.sync_fcl_stage_info | B20: L5 BPS 直接对接（阶段聚合） | C20: BPS 聚合 Stage/Timeline 表(57 列)——各阶段停留天数/时间线。 BPS Stage 面板数据源。 | D20: 查 BPS 各阶段天数落库值。 | E20: 阶段口径在 Redshift 算清后同步；JOIN portfunding 带 funding 维。 | F20: 1 行/贷款/fctrdt（过滤 activefcflag=1 且 fcremovaldate IS NULL）。 | G20: port.fcl_stage_info(⋈ port.portfunding) → bpms.sync_fcl_stage_info〔GET_FCL_STAGE_DATA asset_managment_config.py:925-929〕 | H20: port.fcl_stage_info、port.portfunding | I20: → bpms.biz_data_view_loan_details_foreclosure(视图) → BPS Stage 面板 | J20: bpms.biz_data_view_loan_details_foreclosure
A21: ⑳ bpms.biz_data_view_loan_details_foreclosure | B21: L5 BPS 详情页视图 | C21: BPS 法拍详情页视图(104 列)——把主表 + stage + hold + lm + bk 用 LEFT JOIN 拼成详情页；含 actual/var 天数。 BPS 详情页的‘一站式’读取视图。 | D21: 查详情页某列从哪几张 sync 表拼来、actual vs target 差异。 | E21: 详情页要跨 5 张面板表聚合，用视图免去前端多次查询。 | F21: 1 行/贷款/fctrdt（取最新）。 | G21: { bpms.sync_loan_foreclosure + bpms.sync_fcl_stage_info + bpms.sync_loan_foreclosure_hold + bpms.sync_loan_foreclosure_loss_mitigation + bpms.sync_loan_foreclosure_bankruptcy } → 视图(LEFT JOIN，104 列) | H21: bpms.sync_loan_foreclosure、bpms.sync_fcl_stage_info、bpms.sync_loan_foreclosure_hold、bpms.sync_loan_foreclosure_loss_mitigation、bpms.sync_loan_foreclosure_bankruptcy | I21: → BPS 法拍详情页 UI（5 面板） | J21: BPS 法拍详情页 UI
A22: ㉑ bpms.sync_loan_foreclosure_hold | B22: L5 BPS 直接对接（Hold 历史） | C22: BPS Hold 全历史(每次变更一行)。 BPS Hold 面板。 | D22: 查 BPS 上某贷款全部 Hold 落库记录。 | E22: 见 ⑫；L4 拆槽后同步覆盖更新。 | F22: 1 行/Hold 段。 | G22: port.basic_data_loan_foreclosure_hold → bpms.sync_loan_foreclosure_hold〔asset_managment_config.py:847-894〕 | H22: port.basic_data_loan_foreclosure_hold | I22: → bpms.biz_data_view_loan_details_foreclosure(视图) → BPS Hold 面板 | J22: bpms.biz_data_view_loan_details_foreclosure
A23: ㉒ bpms.sync_loan_foreclosure_loss_mitigation | B23: L5 BPS 直接对接（LM 周期历史） | C23: BPS LM 周期历史(1 行/LM 周期，已解码)。 BPS LM 面板。 | D23: 查 BPS 上某贷款全部 LM 周期落库记录。 | E23: 见 ⑬；L4 解码后同步覆盖更新。 | F23: 1 行/LM 周期。 | G23: port.basic_data_loan_foreclosure_loss_mitigation → bpms.sync_loan_foreclosure_loss_mitigation〔asset_managment_config.py:799-819〕 | H23: port.basic_data_loan_foreclosure_loss_mitigation | I23: → bpms.biz_data_view_loan_details_foreclosure(视图) → BPS LM 面板 | J23: bpms.biz_data_view_loan_details_foreclosure
A24: ㉓ bpms.sync_loan_foreclosure_bankruptcy | B24: L5 BPS 直接对接（破产记录） | C24: BPS 破产记录(1 行/破产申请，已解码)。 BPS 破产面板。 | D24: 查 BPS 上某贷款全部破产记录落库值。 | E24: 见 ⑭；L4 解码后同步覆盖更新。 | F24: 1 行/破产申请。 | G24: port.basic_data_loan_foreclosure_bankruptcy → bpms.sync_loan_foreclosure_bankruptcy〔asset_managment_config.py:822-843〕 | H24: port.basic_data_loan_foreclosure_bankruptcy | I24: → bpms.biz_data_view_loan_details_foreclosure(视图) → BPS 破产面板 | J24: bpms.biz_data_view_loan_details_foreclosure
A25: ㉔ newrez.portnewrezdatadic | B25: 字典（Newrez 解码字典） | C25: Newrez FCL 解码字典(8 列)——把 LM/BK 等编码(LMDeal/LMProgram/LMStatus/LMDecision/BKStatus 等)映射成业务文案。 给 LM/BK 等表的编码解码提供查找表。 | D25: 查某编码的业务含义、核对解码是否正确。 | E25: 源表存编码省空间，展示需文案；统一一张字典 JOIN 解码(COALESCE(dict_desc, raw_code))。 | F25: 1 行/(field_name, code)。 | G25: Servicer(Newrez) 文件(L0) → newrez.portnewrezdatadic | H25: Servicer 文件(S3, L0) | I25: ⋈ basic_data_pool_config.py(LM :835-840 / BK :367) → port.basic_data_loan_foreclosure_loss_mitigation / _bankruptcy(解码列) → bpms.sync_loan_foreclosure_loss_mitigation / _bankruptcy → 视图 → BPS | J25: port.basic_data_loan_foreclosure_loss_mitigation、port.basic_data_loan_foreclosure_bankruptcy、bpms.sync_loan_foreclosure_loss_mitigation、bpms.sync_loan_foreclosure_bankruptcy

Sheet ① 表清单 索引
A1: doc 19 — 5 个样例贷款 · FCL 全链路全表全字段原始转储（prod）
A2: 文档目的 | B2: 把 5 个样例贷款在 FCL 全链路【所有表的全部字段】逐一列出（一个 sheet 一张表），完整呈现 Newrez 源 → Redshift 中间层 → BPS 的「业务 ↔ 数据」对应关系。doc 16 仅含各面板用到的部分字段，本表是其原始数据底座。
A3: 数据来源 | B3: 全部 prod（只读）：mysql_prod（bpms + newrez 源）+ redshift_prod（port 中间层）。由 scripts/fetch_fcl_sample_raw_dump_data.py 预取到 outputs/fcl_sample_raw_dump_data.json。
A4: 目标读者 | B4: 数据工程师 · 业务分析师 · 验证人员 · 接入工程师 · 未来 AI 会话
A5: 取数口径 | B5: Newrez 源 / Redshift 快照表 dataasof=MAX(每贷款)；stage/视图 fctrdt=MAX(每贷款)；sync 基础表当前态；多行表(hold/lm/bk)取全历史。日期统一 YYYY-MM-DD；空值显示 —。业务日对齐 2026-06-01。
A6: 排版 | B6: 1 行/贷款的表 → 转置（字段为行 × 5 贷款列）；多行/贷款的表 → 平铺（记录为行 × 全字段列）。
A7: 修订历史 | B7: 2026-06-06 v4：补 doc 21 §0.1 图缺的逾期支线 L2/L3 + 改名临时表共 3 张中间表（temp_basic_data_fcl / basic_data_daily_loan_common / _clean），全链路 20→23 表。2026-06-04 v3：每表加「查询 SQL」行 + 新增解码字典 sheet（portnewrezdatadic）。2026-06-04 v2：改用 prod 重取 + 新增 Redshift 中间层 8 表。2026-06-03 v1：dev · 12 sheet。
A9: 一、Newrez 源数据表（mysql_prod.newrez）
A10: Sheet | B10: 表 / 视图 | C10: 用途 | D10: 列数 | E10: 本dump行/命中
A11: ② src·portnewrezfc | B11: newrez.portnewrezfc | C11: FCL 主源表（时间线/状态/Hold槽/金额/律师） | D11: 63 | E11: 5/5 贷款
A12: ③ src·portnewrezbk | B12: newrez.portnewrezbk | C12: 破产源表 | D12: 60 | E12: 5/5 贷款
A13: ④ src·portnewrezlm | B13: newrez.portnewrezlm | C13: 损失缓解(LM)源表 | D13: 56 | E13: 5/5 贷款
A14: ⑤ src·portnewrezgeneral | B14: newrez.portnewrezgeneral | C14: 通用源表（legalstatus / delinquency_status_mba 等） | D14: 125 | E14: 5/5 贷款
A15: ⑥ src·portnewrezprop | B15: newrez.portnewrezprop | C15: 房产源表（propertystate 等） | D15: 32 | E15: 5/5 贷款
A16: 二、Redshift 中间层（redshift_prod.port）
A17: Sheet | B17: 表 / 视图 | C17: 用途 | D17: 列数 | E17: 本dump行/命中
A18: ⑦ mid·basic_data_loan_fcl | B18: port.basic_data_loan_fcl | C18: Redshift FCL 快照中间表（portnewrezfc 全量进此；每贷款取最新 dataasof） | D18: 61 | E18: 5/5 贷款
A19: ⑧ mid·basic_data_loan_foreclosure | B19: port.basic_data_loan_foreclosure | C19: Redshift FCL 聚合表（1 行/贷款，sync_loan_foreclosure 的直接上游） | D19: 62 | E19: 5/5 贷款
A20: ⑨ mid·basic_data_fcl_related | B20: port.basic_data_fcl_related | C20: FCL 关联/过滤中间表（delq_status 等；每贷款最新 dataasof） | D20: 14 | E20: 5/5 贷款
A21: ⑩ mid·fcl_stage_info(RS) | B21: port.fcl_stage_info | C21: Redshift 阶段表（sync_fcl_stage_info 上游；每贷款最新 fctrdt） | D21: 48 | E21: 5/5 贷款
A22: ⑪ mid·portfunding | B22: port.portfunding | C22: 融资池表（入库 JOIN 过滤；1 行/贷款） | D22: 57 | E22: 5/5 贷款
A23: ⑫ mid·hold | B23: port.basic_data_loan_foreclosure_hold | C23: Redshift Hold 历史（sync_loan_foreclosure_hold 上游） | D23: 17 | E23: 21 行
A24: ⑬ mid·loss_mitigation | B24: port.basic_data_loan_foreclosure_loss_mitigation | C24: Redshift LM 历史（上游） | D24: 16 | E24: 21 行
A25: ⑭ mid·bankruptcy | B25: port.basic_data_loan_foreclosure_bankruptcy | C25: Redshift 破产历史（上游） | D25: 15 | E25: 3 行
A26: ⑮ mid·temp_basic_data_fcl | B26: tempfc.temp_basic_data_fcl | C26: Redshift 改名临时表（portnewrezfc 等原始列→统一列；运行时中间产物，basic_data_loan_fcl 的上游） | D26: 37 | E26: 5/5 贷款
A27: ⑯ mid·daily_loan_common | B27: port.basic_data_daily_loan_common | C27: 逾期支线 L2 统一日表（delq_status；每贷款最新 asofdate） | D27: 78 | E27: 5/5 贷款
A28: ⑰ mid·daily_loan_common_clean | B28: port.basic_data_daily_loan_common_clean | C28: 逾期支线 L3 清洗日表（delinq / days360；每贷款最新 fctrdt） | D28: 103 | E28: 5/5 贷款
A29: 三、BPS 直接对接表（mysql_prod.bpms）
A30: Sheet | B30: 表 / 视图 | C30: 用途 | D30: 列数 | E30: 本dump行/命中
A31: ⑱ bps·sync_loan_foreclosure | B31: bpms.sync_loan_foreclosure | C31: Summary/Timeline/target 主表 | D31: 72 | E31: 4/5 贷款
A32: ⑲ bps·sync_fcl_stage_info | B32: bpms.sync_fcl_stage_info | C32: 聚合 Stage/Timeline 表 | D32: 57 | E32: 5/5 贷款
A33: ⑳ bps·view_loan_details | B33: bpms.biz_data_view_loan_details_foreclosure（视图） | C33: 详情页视图（actual/var 天数；每贷款最新 fctrdt） | D33: 104 | E33: 5/5 贷款
A34: ㉑ bps·hold | B34: bpms.sync_loan_foreclosure_hold | C34: Hold 全历史（每次变更一行） | D34: 15 | E34: 21 行
A35: ㉒ bps·loss_mitigation | B35: bpms.sync_loan_foreclosure_loss_mitigation | C35: LM 周期历史 | D35: 22 | E35: 21 行
A36: ㉓ bps·bankruptcy | B36: bpms.sync_loan_foreclosure_bankruptcy | C36: 破产记录 | D36: 22 | E36: 3 行
A37: 四、解码字典（redshift_prod.newrez.portnewrezdatadic）
A38: Sheet | B38: 表 | C38: 用途 | D38: 字段 | E38: 本5贷款用到
A39: ㉔ dict·portnewrezdatadic | B39: newrez.portnewrezdatadic | C39: FCL 解码字典（仅列 5 样例用到的码；完整见数据字典 表26） | D39: 8 | E39: 55 码
A40: 不纳入本转储的表
A41: — | B41: port.basic_data_fcl_stage | C41: 较旧的阶段中间表（实测仅到 2025-09，已被 port.fcl_stage_info 取代）
A43: 样例贷款（5）
A44: Loan 1 | B44: 7727000088 —— Judicial(FL)·JUDGEMENT·Hold×7·LM×9
A45: Loan 2 | B45: 7727000672 —— Non-Judicial(MI)·REFERRAL
A46: Loan 3 | B46: 7727004200 —— Judicial(IL)·SALE
A47: Loan 4 | B47: 7727000065 —— BK + Hold×4 + 完结REO
A48: Loan 5 | B48: 7727000010 —— Chapter 13 Active BK（未入 FCL 管道）

Sheet ② src·portnewrezfc
A1: newrez.portnewrezfc — FCL 主源表（时间线/状态/Hold槽/金额/律师）
A2: 全 63 字段 · 取数口径：dataasof=MAX(每贷款) · 命中 5/5 贷款（无行的贷款列显示 —） · prod 实测 2026-06-04 · 业务日 2026-06-01
A3: 查询 SQL（prod 只读）： -- newrez.portnewrezfc · mysql_prod(只读) · 每贷款 dataasof=MAX(最新快照) · 业务日 2026-06-01 SELECT t.* FROM newrez.portnewrezfc t JOIN (SELECT loanid, MAX(dataasof) AS _md FROM newrez.portnewrezfc WHERE loanid IN ('7727000088','7727000672','7727004200','7727000065','7727000010') GROUP BY loanid) m ON t.loanid=m.loanid AND t.dataasof=m._md;
A4: 📋 业务含义与全链路血缘 〔自动生成·勿手改本块；改 outputs/fcl_table_meta.json 后重跑〕
A5: 业务含义/目的：Newrez 每日推送的法拍(FCL)主源表——一笔贷款一行最新快照，含 FCL 时间线里程碑(setup/referral/firstlegal/judgment/sale)、当前阶段 fcstage、4 个 Hold 槽(fchold1..4)、拍卖金额、律师等。 Newrez 法拍全流程的原始事实底座；下游所有 FCL 计算的源头。
A6: 何时来查：想看某贷款 Newrez 原始报的 FCL 里程碑/阶段/Hold 原值，或核对下游计算是否忠实于源时。
A7: 为什么这样处理：各 Servicer 文件格式不同，先按‘一家一张原始表’落地保真，再到 L4 统一改名/UNION，便于回溯与对账。
A8: 数据粒度：1 行/贷款/dataasof（每日快照）；本 dump 取 dataasof=MAX。
A9: 上游链路：Servicer 文件(S3, L0) → newrez.portnewrezfc 〔load_daily_newrez_flow.py；落库 daily_task.py:923-942(MySQL)/960-983(Redshift)〕
A10: 全部上游表：Servicer 文件(S3, L0)
A11: 下游链路：portnewrezfc → tempfc.temp_basic_data_fcl(改名) → port.basic_data_loan_fcl(全 servicer UNION，FCL 事实表) → { port.basic_data_loan_foreclosure〔GEN_FCL_DETAIL basic_data_pool_config.py:253-305〕 / port.fcl_stage_info〔GEN_FCL_STAGE :1774-2440〕 / port.basic_data_loan_foreclosure_hold〔Hold 拆槽 :466-768〕 } → bpms.sync_*〔asset_managment_config.py〕 → bpms.biz_data_view_loan_details_foreclosure(视图) → BPS 法拍面板
A12: 全部下游表：tempfc.temp_basic_data_fcl、port.basic_data_loan_fcl、port.basic_data_loan_foreclosure、port.fcl_stage_info、port.basic_data_loan_foreclosure_hold、bpms.sync_loan_foreclosure、bpms.sync_fcl_stage_info、bpms.sync_loan_foreclosure_hold、bpms.biz_data_view_loan_details_foreclosure
A13: ▲ 以上为「业务含义与全链路血缘」说明块；下方为原始数据 ────
A14: 字段 | B14: 7727000088 | C14: 7727000672 | D14: 7727004200 | E14: 7727000065 | F14: 7727000010
A15: id | B15: 1750674 | C15: 1750233 | D15: 1751818 | E15: 1750695 | F15: 1750688
A16: loanid | B16: 7727000088 | C16: 7727000672 | D16: 7727004200 | E16: 7727000065 | F16: 7727000010
A17: dataasof | B17: 2026-06-04 | C17: 2026-06-04 | D17: 2026-06-04 | E17: 2026-06-04 | F17: 2026-06-04
A18: shellpointloanid | B18: 1031718838 | C18: 1032761570 | D18: 0688132141 | E18: 1031718621 | F18: 1031718692
A19: fcsetupdate | B19: 2025-05-23 | C19: 2026-03-09 | D19: 2025-06-27 | E19: 2025-02-03 | F19: —
A20: fcreferraldate | B20: 2025-05-23 | C20: 2026-03-09 | D20: 2025-06-27 | E20: 2025-02-03 | F20: —
A21: smsdaysinfc | B21: 368 | C21: 79 | D21: 294 | E21: 254 | F21: —
A22: daysinfc | B22: 368 | C22: 79 | D22: 294 | E22: 254 | F22: —
A23: demandsentdate | B23: 2025-02-18 | C23: 2025-11-17 | D23: 2025-05-20 | E23: 2024-08-12 | F23: 2026-04-10
A24: demandexpirationdate | B24: 2025-03-25 | C24: 2025-12-22 | D24: 2025-06-24 | E24: 2024-09-18 | F24: 2026-05-15
A25: fcstage | B25: Post Sale Review (SCRA and PACER Check) | C25: Pre-Sale Review 1 (SCRA and PACER Check) | D25: Pre-Sale Review 1 (SCRA and PACER Check) | E25: Post Sale Review (SCRA and PACER Check) | F25: —
... A77: srliensaledate | B77: — | C77: — | D77: — | E77: — | F77: —

Sheet ③ src·portnewrezbk
A1: newrez.portnewrezbk — 破产源表
A2: 全 60 字段 · 取数口径：dataasof=MAX(每贷款) · 命中 5/5 贷款（无行的贷款列显示 —） · prod 实测 2026-06-04 · 业务日 2026-06-01
A3: 查询 SQL（prod 只读）： -- newrez.portnewrezbk · mysql_prod(只读) · 每贷款 dataasof=MAX(最新快照) · 业务日 2026-06-01 SELECT t.* FROM newrez.portnewrezbk t JOIN (SELECT loanid, MAX(dataasof) AS _md FROM newrez.portnewrezbk WHERE loanid IN ('7727000088','7727000672','7727004200','7727000065','7727000010') GROUP BY loanid) m ON t.loanid=m.loanid AND t.dataasof=m._md;
A4: 📋 业务含义与全链路血缘 〔自动生成·勿手改本块；改 outputs/fcl_table_meta.json 后重跑〕
A5: 业务含义/目的：Newrez 破产(BK)源表，按贷款×破产申请记录，含 bkstatus/bkchapter/bkfileddate 等编码字段。 BK 事实底座；为 FCL 提供‘是否在破产保护(暂停法拍)’的判断。
A6: 何时来查：查某贷款原始破产章节/状态/申请日，或核对 BPS 破产面板。
A7: 为什么这样处理：破产是法拍的暂停因素，需单列保真；编码值经 datadic 解码成业务文案。
A8: 数据粒度：1 行/贷款/破产申请(bkfileddate)；多次申请多行。
A9: 上游链路：Servicer 文件(S3, L0) → newrez.portnewrezbk
A10: 全部上游表：Servicer 文件(S3, L0)
A11: 下游链路：portnewrezbk → port.basic_data_loan_foreclosure_bankruptcy〔解码 bkstatus，basic_data_pool_config.py:331-370，JOIN newrez.portnewrezdatadic〕 → bpms.sync_loan_foreclosure_bankruptcy〔asset_managment_config.py:822-843〕 → bpms.biz_data_view_loan_details_foreclosure(视图) → BPS 破产面板
A12: 全部下游表：port.basic_data_loan_foreclosure_bankruptcy、bpms.sync_loan_foreclosure_bankruptcy、bpms.biz_data_view_loan_details_foreclosure
A13: ▲ 以上为「业务含义与全链路血缘」说明块；下方为原始数据 ────
A14: 字段 | B14: 7727000088 | C14: 7727000672 | D14: 7727004200 | E14: 7727000065 | F14: 7727000010
A15: id | B15: 1750674 | C15: 1750233 | D15: 1751818 | E15: 1750695 | F15: 1750688
A16: loanid | B16: 7727000088 | C16: 7727000672 | D16: 7727004200 | E16: 7727000065 | F16: 7727000010
A17: dataasof | B17: 2026-06-04 | C17: 2026-06-04 | D17: 2026-06-04 | E17: 2026-06-04 | F17: 2026-06-04
A18: shellpointloanid | B18: 1031718838 | C18: 1032761570 | D18: 0688132141 | E18: 1031718621 | F18: 1031718692
A19: bkfileddate | B19: — | C19: — | D19: — | E19: 2025-04-30 | F19: 2024-02-06
A20: bkstatus | B20: — | C20: — | D20: — | E20: 2 | F20: 1
A21: bkremovalcode | B21: — | C21: — | D21: — | E21: 1 | F21: —
A22: bkremovaldate | B22: — | C22: — | D22: — | E22: 2025-07-29 | F22: —
A23: bkchapter | B23: — | C23: — | D23: — | E23: 7 | F23: 13
A24: bkcasenumber | B24: — | C24: — | D24: — | E24: 2500228 | F24: 2310152
A25: bkpostpetitionduedate | B25: — | C25: — | D25: — | E25: — | F25: 2026-06-01
... A74: bkfilingregion | B74: — | C74: — | D74: — | E74: Northern District of WV (Martinsburg) | F74: Northern District of Florida, Gainesville Division

Sheet ④ src·portnewrezlm
A1: newrez.portnewrezlm — 损失缓解(LM)源表
A2: 全 56 字段 · 取数口径：dataasof=MAX(每贷款) · 命中 5/5 贷款（无行的贷款列显示 —） · prod 实测 2026-06-04 · 业务日 2026-06-01
A3: 查询 SQL（prod 只读）： -- newrez.portnewrezlm · mysql_prod(只读) · 每贷款 dataasof=MAX(最新快照) · 业务日 2026-06-01 SELECT t.* FROM newrez.portnewrezlm t JOIN (SELECT loanid, MAX(dataasof) AS _md FROM newrez.portnewrezlm WHERE loanid IN ('7727000088','7727000672','7727004200','7727000065','7727000010') GROUP BY loanid) m ON t.loanid=m.loanid AND t.dataasof=m._md;
A4: 📋 业务含义与全链路血缘 〔自动生成·勿手改本块；改 outputs/fcl_table_meta.json 后重跑〕
A5: 业务含义/目的：Newrez 损失缓解(LM)源表，按贷款×LM 周期(dealstartdate)，含 lmdeal/lmprogram/lmstatus/lmdecision 等编码。 LM 事实底座；提供‘是否在协商还款方案(暂停/替代法拍)’。
A6: 何时来查：查某贷款 LM 周期/项目/决定原值，或核对 BPS LM 面板。
A7: 为什么这样处理：LM 是法拍的替代/暂停路径，需单列保真；编码经 datadic 解码。
A8: 数据粒度：1 行/贷款/LM 周期(dealstartdate)；多周期多行。
A9: 上游链路：Servicer 文件(S3, L0) → newrez.portnewrezlm
A10: 全部上游表：Servicer 文件(S3, L0)
A11: 下游链路：portnewrezlm → port.basic_data_loan_foreclosure_loss_mitigation〔basic_data_pool_config.py:799-843，JOIN newrez.portnewrezdatadic〕 → bpms.sync_loan_foreclosure_loss_mitigation〔asset_managment_config.py:799-819〕 → bpms.biz_data_view_loan_details_foreclosure(视图) → BPS LM 面板
A12: 全部下游表：port.basic_data_loan_foreclosure_loss_mitigation、bpms.sync_loan_foreclosure_loss_mitigation、bpms.biz_data_view_loan_details_foreclosure
A13: ▲ 以上为「业务含义与全链路血缘」说明块；下方为原始数据 ────
A14: 字段 | B14: 7727000088 | C14: 7727000672 | D14: 7727004200 | E14: 7727000065 | F14: 7727000010
A15: id | B15: 1747370 | C15: 1746929 | D15: 1748514 | E15: 1747391 | F15: 1747384
A16: loanid | B16: 7727000088 | C16: 7727000672 | D16: 7727004200 | E16: 7727000065 | F16: 7727000010
A17: dataasof | B17: 2026-06-04 | C17: 2026-06-04 | D17: 2026-06-04 | E17: 2026-06-04 | F17: 2026-06-04
A18: shellpointloanid | B18: 1031718838 | C18: 1032761570 | D18: 0688132141 | E18: 1031718621 | F18: 1031718692
A19: hardshiptype | B19: 11 | C19: 11 | D19: 20 | E19: 11 | F19: 12
A20: borrowerintention | B20: — | C20: — | D20: — | E20: — | F20: —
A21: lmdeal | B21: 7 | C21: 4 | D21: 1 | E21: 2 | F21: 1
A22: dealstartdate | B22: 2026-02-17 | C22: 2026-02-25 | D22: 2026-01-06 | E22: 2025-07-01 | F22: 2026-04-16
A23: daysindeal | B23: 66 | C23: 99 | D23: 27 | E23: 0 | F23: 12
A24: lmstatus | B24: 112 | C24: 25 | D24: 5 | E24: 166 | F24: 112
A25: statusstartdate | B25: 2026-04-22 | C25: 2026-03-24 | D25: 2026-01-14 | E25: 2024-11-26 | F25: 2026-04-23
... A70: investorloanid | B70: 7727000088 | C70: 7727000672 | D70: 7727004200 | E70: 7727000065 | F70: 7727000010

Sheet ⑤ src·portnewrezgeneral
A1: newrez.portnewrezgeneral — 通用源表（legalstatus / delinquency_status_mba 等）
A2: 全 125 字段 · 取数口径：dataasof=MAX(每贷款) · 命中 5/5 贷款（无行的贷款列显示 —） · prod 实测 2026-06-04 · 业务日 2026-06-01
A3: 查询 SQL（prod 只读）： -- newrez.portnewrezgeneral · mysql_prod(只读) · 每贷款 dataasof=MAX(最新快照) · 业务日 2026-06-01 SELECT t.* FROM newrez.portnewrezgeneral t JOIN (SELECT loanid, MAX(dataasof) AS _md FROM newrez.portnewrezgeneral WHERE loanid IN ('7727000088','7727000672','7727004200','7727000065','7727000010') GROUP BY loanid) m ON t.loanid=m.loanid AND t.dataasof=m._md;
A4: 📋 业务含义与全链路血缘 〔自动生成·勿手改本块；改 outputs/fcl_table_meta.json 后重跑〕
A5: 业务含义/目的：Newrez 通用源表(125 列)，含 legalstatus、delinquency_status_mba(MBA 逾期分类)、nextduedate 等账户层属性。 逾期(delinquency)支线的源头；提供 delq_status 原值。
A6: 何时来查：查某贷款原始逾期分类/法律状态/下次到期日。
A7: 为什么这样处理：逾期与 FCL 是两条支线——逾期来自 general 表经 days360 归一，FCL 来自 portnewrezfc 显式标志；二者在 L4 汇合。FCL 码绝不由 days360 推导。
A8: 数据粒度：1 行/贷款/dataasof。
A9: 上游链路：Servicer 文件(S3, L0) → newrez.portnewrezgeneral
A10: 全部上游表：Servicer 文件(S3, L0)
A11: 下游链路：portnewrezgeneral.delinquency_status_mba → port.portdaily_v2〔portdaily_config.py〕 → port.basic_data_daily_loan_common.delq_status(逾期支线 L2，daily_data_loan_common_config.py) → port.basic_data_daily_loan_common_clean.delinq(L3，daily_data_loan_common_clean_config.py，CASE+days360) → { port.basic_data_fcl_related.delq_status / port.fcl_stage_info.group / port.portmonthbase } → BPS
A12: 全部下游表：port.portdaily_v2、port.basic_data_daily_loan_common、port.basic_data_daily_loan_common_clean、port.basic_data_fcl_related、port.fcl_stage_info、port.portmonthbase、bpms.sync_fcl_stage_info
A13: ▲ 以上为「业务含义与全链路血缘」说明块；下方为原始数据 ────
A14: 字段 | B14: 7727000088 | C14: 7727000672 | D14: 7727004200 | E14: 7727000065 | F14: 7727000010
A15: id | B15: 1749124 | C15: 1748683 | D15: 1750268 | E15: 1749145 | F15: 1749138
A16: loanid | B16: 7727000088 | C16: 7727000672 | D16: 7727004200 | E16: 7727000065 | F16: 7727000010
A17: dataasof | B17: 2026-06-04 | C17: 2026-06-04 | D17: 2026-06-04 | E17: 2026-06-04 | F17: 2026-06-04
A18: shellpointloanid | B18: 1031718838 | C18: 1032761570 | D18: 0688132141 | E18: 1031718621 | F18: 1031718692
A19: investorid | B19: BI2726 | C19: BI2725 | D19: BIRTT1 | E19: TT1REO | F19: BI2726
A20: investorloanid | B20: 7727000088 | C20: 7727000672 | D20: 7727004200 | E20: 7727000065 | F20: 7727000010
A21: priorservicerloannumber | B21: 9010021155 | C21: 32288235 | D21: 3260057082 | E21: 9014327961 | F21: 9014059868
A22: boarddate | B22: 2024-07-04 | C22: 2024-07-04 | D22: 2024-02-07 | E22: 2024-07-04 | F22: 2024-07-04
A23: acquisitiondate | B23: 2024-07-02 | C23: 2024-07-02 | D23: 2024-02-01 | E23: 2024-07-02 | F23: 2024-07-02
A24: acquisitionbalance | B24: 318856.09 | C24: 421270.39 | D24: 455612.06 | E24: 470399.51 | F24: 271997.47
A25: mbadelinquency | B25: 14 | C25: 6 | D25: 15 | E25: 14 | F25: 9
... A139: successorservicer | B139: — | C139: — | D139: — | E139: — | F139: —

Sheet ⑥ src·portnewrezprop
A1: newrez.portnewrezprop — 房产源表（propertystate 等）
A2: 全 32 字段 · 取数口径：dataasof=MAX(每贷款) · 命中 5/5 贷款（无行的贷款列显示 —） · prod 实测 2026-06-04 · 业务日 2026-06-01
A3: 查询 SQL（prod 只读）： -- newrez.portnewrezprop · mysql_prod(只读) · 每贷款 dataasof=MAX(最新快照) · 业务日 2026-06-01 SELECT t.* FROM newrez.portnewrezprop t JOIN (SELECT loanid, MAX(dataasof) AS _md FROM newrez.portnewrezprop WHERE loanid IN ('7727000088','7727000672','7727004200','7727000065','7727000010') GROUP BY loanid) m ON t.loanid=m.loanid AND t.dataasof=m._md;
A4: 📋 业务含义与全链路血缘 〔自动生成·勿手改本块；改 outputs/fcl_table_meta.json 后重跑〕
A5: 业务含义/目的：Newrez 房产源表(32 列)，含 propertystate(州，定司法/非司法)、LTV、occupancy 等。 提供物业/州属性；州决定 FCL 走司法(judicial)还是非司法路径。
A6: 何时来查：查某贷款物业州/LTV/占用情况。
A7: 为什么这样处理：司法/非司法影响 FCL 时长与阶段口径，需物业州维度（实测 state 取自 portnewrezprop.propertystate）。
A8: 数据粒度：1 行/贷款/dataasof。
A9: 上游链路：Servicer 文件(S3, L0) → newrez.portnewrezprop
A10: 全部上游表：Servicer 文件(S3, L0)
A11: 下游链路：portnewrezprop.propertystate → port.basic_data_daily_loan_common(州维度) / port.basic_data_loan_foreclosure(summary_judicial_foreclosure 司法标志) → bpms.sync_loan_foreclosure → BPS
A12: 全部下游表：port.basic_data_daily_loan_common、port.basic_data_loan_foreclosure、bpms.sync_loan_foreclosure
A13: ▲ 以上为「业务含义与全链路血缘」说明块；下方为原始数据 ────
A14: 字段 | B14: 7727000088 | C14: 7727000672 | D14: 7727004200 | E14: 7727000065 | F14: 7727000010
A15: id | B15: 1747370 | C15: 1746929 | D15: 1748514 | E15: 1747391 | F15: 1747384
A16: loanid | B16: 7727000088 | C16: 7727000672 | D16: 7727004200 | E16: 7727000065 | F16: 7727000010
A17: dataasof | B17: 2026-06-04 | C17: 2026-06-04 | D17: 2026-06-04 | E17: 2026-06-04 | F17: 2026-06-04
A18: shellpointloanid | B18: 1031718838 | C18: 1032761570 | D18: 0688132141 | E18: 1031718621 | F18: 1031718692
A19: propertyaddressline1 | B19: 21 LK CHARLES LN | C19: W 3120 SCHLOSSER RD | D19: 13977 W EMMA LN | E19: 2331 SW FREEMAN ST | F19: 19801 OLD BELLAMY RD
A20: propertyaddressline2 | B20: — | C20: — | D20: — | E20: — | F20: —
A21: propertycity | B21: PALM COAST | C21: MORAN | D21: METTAWA | E21: PORT SAINT LUCIE | F21: ALACHUA
A22: propertystate | B22: FL | C22: MI | D22: IL | E22: FL | F22: FL
A23: propertyzip | B23: 32137 | C23: 49760 | D23: 60045 | E23: 34953 | F23: 32615
A24: propertycounty | B24: FLAGLER | C24: MACKINAC | D24: LAKE | E24: ST. LUCIE | F24: ALACHUA
A25: propertytype | B25: 20 | C25: 20 | D25: 39 | E25: 20 | F25: 20
... A46: countycode | B46: 35 | C46: 97 | D46: 97 | E46: 111 | F46: 1

Sheet ⑦ mid·basic_data_loan_fcl
A1: port.basic_data_loan_fcl — Redshift FCL 快照中间表（portnewrezfc 全量进此；每贷款取最新 dataasof）
A2: 全 61 字段 · 取数口径：dataasof=MAX(每贷款) · 命中 5/5 贷款（无行的贷款列显示 —） · prod 实测 2026-06-04 · 业务日 2026-06-01
A3: 查询 SQL（prod 只读）： -- port.basic_data_loan_fcl · redshift_prod(只读) · 每贷款 dataasof=MAX(最新快照) · 业务日 2026-06-01 SELECT t.* FROM port.basic_data_loan_fcl t JOIN (SELECT loanid, MAX(dataasof) AS _md FROM port.basic_data_loan_fcl WHERE loanid IN ('7727000088','7727000672','7727004200','7727000065','7727000010') GROUP BY loanid) m ON t.loanid=m.loanid AND t.dataasof=m._md;
A4: 📋 业务含义与全链路血缘 〔自动生成·勿手改本块；改 outputs/fcl_table_meta.json 后重跑〕
A5: 业务含义/目的：Redshift FCL 事实表——portnewrezfc 等经改名后 UNION 全 6 家 servicer 的统一列宽表(每贷款最新 dataasof)。 FCL 计算的统一入口；屏蔽各 servicer 列名差异。
A6: 何时来查：查‘统一列名后的 FCL 字段值’，或定位某下游字段来自哪根统一列。
A7: 为什么这样处理：各家列名不同，先改名(tempfc.temp_basic_data_fcl)再 UNION 成一张统一事实表，下游只面对一套列名。
A8: 数据粒度：1 行/贷款（每贷款最新 dataasof）。
A9: 上游链路：Servicer 文件(L0) → newrez.portnewrezfc(+各家对应表) → tempfc.temp_basic_data_fcl(改名) → port.basic_data_loan_fcl〔UNION，basic_data_pool_config.py〕
A10: 全部上游表：Servicer 文件(L0)、newrez.portnewrezfc、(sls/carrington/mrc/fci/selene 对应源表)、tempfc.temp_basic_data_fcl
A11: 下游链路：basic_data_loan_fcl → { port.basic_data_loan_foreclosure〔GEN_FCL_DETAIL :253-305〕 / port.fcl_stage_info〔GEN_FCL_STAGE :1774-2440〕 / port.basic_data_loan_foreclosure_hold〔:466-768〕 / port.basic_data_loan_foreclosure_loss_mitigation〔:799-843〕 / port.basic_data_loan_foreclosure_bankruptcy〔:331-370〕 } → bpms.sync_* → 视图 → BPS
A12: 全部下游表：port.basic_data_loan_foreclosure、port.fcl_stage_info、port.basic_data_loan_foreclosure_hold、port.basic_data_loan_foreclosure_loss_mitigation、port.basic_data_loan_foreclosure_bankruptcy、bpms.sync_loan_foreclosure、bpms.sync_fcl_stage_info、bpms.sync_loan_foreclosure_hold、bpms.sync_loan_foreclosure_loss_mitigation、bpms.sync_loan_foreclosure_bankruptcy、bpms.biz_data_view_loan_details_foreclosure
A13: ▲ 以上为「业务含义与全链路血缘」说明块；下方为原始数据 ────
A14: 字段 | B14: 7727000088 | C14: 7727000672 | D14: 7727004200 | E14: 7727000065 | F14: 7727000010
A15: dataasof | B15: 2026-06-04 | C15: 2026-06-04 | D15: 2026-06-04 | E15: 2026-06-04 | F15: 2026-06-04
A16: loanid | B16: 7727000088 | C16: 7727000672 | D16: 7727004200 | E16: 7727000065 | F16: 7727000010
A17: servicer | B17: Newrez | C17: Newrez | D17: Newrez | E17: Newrez | F17: Newrez
A18: svc_loanid | B18: 1031718838 | C18: 1032761570 | D18: 0688132141 | E18: 1031718621 | F18: 1031718692
A19: activefcflag | B19: 0 | C19: 0 | D19: 0 | E19: 0 | F19: 0
A20: titleordereddate | B20: — | C20: — | D20: — | E20: 2025-11-13 | F20: —
A21: titlereceiveddate | B21: — | C21: — | D21: — | E21: 2025-12-02 | F21: —
A22: titlecleardate | B22: — | C22: — | D22: — | E22: — | F22: —
A23: noi_date | B23: — | C23: — | D23: — | E23: — | F23: —
A24: fcsetupdate | B24: 2025-05-23 | C24: 2026-03-09 | D24: 2025-06-27 | E24: 2025-02-03 | F24: —
A25: referral_start_date | B25: 2025-05-23 | C25: 2026-03-09 | D25: 2025-06-27 | E25: 2025-02-03 | F25: —
... A75: holdmodified4 | B75: — | C75: — | D75: — | E75: — | F75: —

Sheet ⑧ mid·basic_data_loan_foreclosu
A1: port.basic_data_loan_foreclosure — Redshift FCL 聚合表（1 行/贷款，sync_loan_foreclosure 的直接上游）
A2: 全 62 字段 · 取数口径：dataasof=MAX(每贷款) · 命中 5/5 贷款（无行的贷款列显示 —） · prod 实测 2026-06-04 · 业务日 2026-06-01
A3: 查询 SQL（prod 只读）： -- port.basic_data_loan_foreclosure · redshift_prod(只读) · 每贷款 dataasof=MAX(最新快照) · 业务日 2026-06-01 SELECT t.* FROM port.basic_data_loan_foreclosure t JOIN (SELECT loanid, MAX(dataasof) AS _md FROM port.basic_data_loan_foreclosure WHERE loanid IN ('7727000088','7727000672','7727004200','7727000065','7727000010') GROUP BY loanid) m ON t.loanid=m.loanid AND t.dataasof=m._md;
A4: 📋 业务含义与全链路血缘 〔自动生成·勿手改本块；改 outputs/fcl_table_meta.json 后重跑〕
A5: 业务含义/目的：Redshift FCL 聚合表(1 行/贷款)——一笔贷款端到端法拍时间线：各里程碑日期、当前状态(summary_foreclosure_status)、司法标志、在法拍天数(summary_days_in_fcl)。 bpms.sync_loan_foreclosure(BPS 主表)的直接上游；法拍主视图的数据底座。
A6: 何时来查：查某贷款法拍‘何时进入各里程碑/当前状态/在法拍多少天/为何退出’。
A7: 为什么这样处理：把事实表里散落的里程碑/状态按业务规则(GEN_FCL_DETAIL CASE)收敛成 1 行/贷款的可读时间线；退出原因直接取 servicer 的 fcremovaldesc(无解码表)。
A8: 数据粒度：1 行/贷款（含在途 + 已结）。
A9: 上游链路：… → port.basic_data_loan_fcl → port.basic_data_loan_foreclosure〔GEN_FCL_DETAIL basic_data_pool_config.py:253-305；状态 CASE :273；司法 :277-279；在法拍天数 :1628〕
A10: 全部上游表：port.basic_data_loan_fcl、tempfc.temp_basic_data_fcl、newrez.portnewrezfc、Servicer 文件(L0)
A11: 下游链路：basic_data_loan_foreclosure → (Redshift→MySQL 同步 df_db_util.py:665-699 sync_to_mysql / 702-726 update_to_mysql) → bpms.sync_loan_foreclosure〔GEN_FORECLOSURE asset_managment_config.py:535-608；实时天数校正 :597-598〕 → bpms.biz_data_view_loan_details_foreclosure(视图) → BPS Summary/Timeline 面板
A12: 全部下游表：bpms.sync_loan_foreclosure、bpms.biz_data_view_loan_details_foreclosure
A13: ▲ 以上为「业务含义与全链路血缘」说明块；下方为原始数据 ────
A14: 字段 | B14: 7727000088 | C14: 7727000672 | D14: 7727004200 | E14: 7727000065 | F14: 7727000010
A15: dataasof | B15: 2026-06-04 | C15: 2026-06-04 | D15: 2026-06-04 | E15: 2026-06-04 | F15: 2026-06-04
A16: loanid | B16: 7727000088 | C16: 7727000672 | D16: 7727004200 | E16: 7727000065 | F16: 7727000010
A17: svcloanid | B17: 1031718838 | C17: 1032761570 | D17: 0688132141 | E17: 1031718621 | F17: 1031718692
A18: servicer | B18: Newrez | C18: Newrez | D18: Newrez | E18: Newrez | F18: Newrez
A19: timeline_notice_of_intent_date | B19: — | C19: — | D19: — | E19: — | F19: —
A20: timeline_notice_of_intent_end_date | B20: — | C20: — | D20: — | E20: — | F20: —
A21: timeline_approved_for_referral_date | B21: — | C21: — | D21: — | E21: — | F21: —
A22: timeline_referred_to_attorney_date | B22: — | C22: — | D22: — | E22: — | F22: —
A23: timeline_referred_to_foreclosure_date | B23: 2025-05-23 | C23: 2026-03-09 | D23: 2025-06-27 | E23: 2025-02-03 | F23: —
A24: timeline_title_report_received_date | B24: — | C24: — | D24: — | E24: 2025-12-02 | F24: —
A25: timeline_preliminary_title_cleared_date | B25: — | C25: — | D25: — | E25: — | F25: —
... A76: summary_last_step_completed_date | B76: 2026-05-26 | C76: 2026-03-25 | D76: 2026-05-19 | E76: 2025-10-15 | F76: —

Sheet ⑨ mid·basic_data_fcl_related
A1: port.basic_data_fcl_related — FCL 关联/过滤中间表（delq_status 等；每贷款最新 dataasof）
A2: 全 14 字段 · 取数口径：dataasof=MAX(每贷款) · 命中 5/5 贷款（无行的贷款列显示 —） · prod 实测 2026-06-04 · 业务日 2026-06-01
A3: 查询 SQL（prod 只读）： -- port.basic_data_fcl_related · redshift_prod(只读) · 每贷款 dataasof=MAX(最新快照) · 业务日 2026-06-01 SELECT t.* FROM port.basic_data_fcl_related t JOIN (SELECT loanid, MAX(dataasof) AS _md FROM port.basic_data_fcl_related WHERE loanid IN ('7727000088','7727000672','7727004200','7727000065','7727000010') GROUP BY loanid) m ON t.loanid=m.loanid AND t.dataasof=m._md;
A4: 📋 业务含义与全链路血缘 〔自动生成·勿手改本块；改 outputs/fcl_table_meta.json 后重跑〕
A5: 业务含义/目的：FCL 关联属性中间表(14 列)——诉讼标志、清算类型、BK 标志、违约原因、delq_status 等。 给 stage 计算与过滤提供‘关联属性/分组键’(delq_status → stage group)。
A6: 何时来查：查某贷款 stage 分组依据、关联诉讼/清算/违约属性。
A7: 为什么这样处理：stage 计算需把逾期支线的 delq_status 与 FCL 属性合并；单列一张关联表承接，避免主时间线表过宽。
A8: 数据粒度：1 行/贷款（最新 dataasof）。
A9: 上游链路：{ port.basic_data_loan_fcl(FCL 属性) + port.basic_data_daily_loan_common_clean.delinq(逾期码) } → port.basic_data_fcl_related〔basic_data_pool_config.py〕
A10: 全部上游表：port.basic_data_loan_fcl、port.basic_data_daily_loan_common_clean
A11: 下游链路：basic_data_fcl_related.delq_status → port.fcl_stage_info.group(stage 分组) → bpms.sync_fcl_stage_info → 视图 → BPS Stage 面板
A12: 全部下游表：port.fcl_stage_info、bpms.sync_fcl_stage_info、bpms.biz_data_view_loan_details_foreclosure
A13: ▲ 以上为「业务含义与全链路血缘」说明块；下方为原始数据 ────
A14: 字段 | B14: 7727000088 | C14: 7727000672 | D14: 7727004200 | E14: 7727000065 | F14: 7727000010
A15: dataasof | B15: 2026-06-04 | C15: 2026-06-04 | D15: 2026-06-04 | E15: 2026-06-04 | F15: 2026-06-04
A16: loanid | B16: 7727000088 | C16: 7727000672 | D16: 7727004200 | E16: 7727000065 | F16: 7727000010
A17: servicer | B17: Newrez | C17: Newrez | D17: Newrez | E17: Newrez | F17: Newrez
A18: delq_status | B18: REO | C18: D120P | D18: P | E18: REO | F18: D60
A19: isloanlitigated | B19: 0 | C19: 0 | D19: 0 | E19: 0 | F19: 0
A20: deactreason | B20: FC-BK | C20: FC-BK | D20: — | E20: FC-BK | F20: —
A21: reasonfordefault | B21: Reduction in Borrower's Income | C21: — | D21: — | E21: Unable to Contact Borrower | F21: —
A22: inauctionflag | B22: 0 | C22: 0 | D22: 0 | E22: 1 | F22: 0
A23: liquidationdate | B23: — | C23: — | D23: 2026-04-16 | E23: — | F23: —
A24: liquidationtype | B24: — | C24: — | D24: 3.0 | E24: — | F24: —
A25: liquidationproceeds | B25: — | C25: — | D25: 503557.98 | E25: — | F25: —
... A28: propertystate | B28: FL | C28: MI | D28: IL | E28: FL | F28: FL

Sheet ⑩ mid·fcl_stage_info(RS)
A1: port.fcl_stage_info — Redshift 阶段表（sync_fcl_stage_info 上游；每贷款最新 fctrdt）
A2: 全 48 字段 · 取数口径：fctrdt=MAX(每贷款) · 命中 5/5 贷款（无行的贷款列显示 —） · prod 实测 2026-06-04 · 业务日 2026-06-01
A3: 查询 SQL（prod 只读）： -- port.fcl_stage_info · redshift_prod(只读) · 每贷款 fctrdt=MAX(最新快照) · 业务日 2026-06-01 SELECT t.* FROM port.fcl_stage_info t JOIN (SELECT loanid, MAX(fctrdt) AS _md FROM port.fcl_stage_info WHERE loanid IN ('7727000088','7727000672','7727004200','7727000065','7727000010') GROUP BY loanid) m ON t.loanid=m.loanid AND t.fctrdt=m._md;
A4: 📋 业务含义与全链路血缘 〔自动生成·勿手改本块；改 outputs/fcl_table_meta.json 后重跑〕
A5: 业务含义/目的：Redshift 阶段表(48 列)——把法拍拆成 6 大阶段，每阶段 5 维(开始/天数/扣除 LM-Hold 重叠等)，每贷款最新 fctrdt。 bpms.sync_fcl_stage_info(BPS 聚合 Stage/Timeline)的上游；面板‘各阶段停留天数’的底座。
A6: 何时来查：查某贷款‘在每个阶段停留多久、扣除 LM/Hold 后净时长、当前在哪个阶段组’。
A7: 为什么这样处理：业务关心‘卡在哪一步多久’；阶段口径复杂(N:N 扣 LM/Hold 重叠)，单列一张表算清，并 JOIN portfunding 取 funding 维。
A8: 数据粒度：1 行/贷款/fctrdt。
A9: 上游链路：{ port.basic_data_loan_fcl + port.basic_data_fcl_related(delq_status 分组) + port.portfunding(JOIN) } → port.fcl_stage_info〔GEN_FCL_STAGE basic_data_pool_config.py:1774-2440〕
A10: 全部上游表：port.basic_data_loan_fcl、port.basic_data_fcl_related、port.basic_data_daily_loan_common_clean、port.portfunding
A11: 下游链路：fcl_stage_info → bpms.sync_fcl_stage_info〔GET_FCL_STAGE_DATA asset_managment_config.py:925-929，JOIN port.portfunding〕 → 视图 → BPS Stage 面板
A12: 全部下游表：bpms.sync_fcl_stage_info、bpms.biz_data_view_loan_details_foreclosure
A13: ▲ 以上为「业务含义与全链路血缘」说明块；下方为原始数据 ────
A14: 字段 | B14: 7727000088 | C14: 7727000672 | D14: 7727004200 | E14: 7727000065 | F14: 7727000010
A15: fctrdt | B15: 2026-05-25 | C15: 2026-05-26 | D15: 2026-04-15 | E15: 2025-10-14 | F15: 2026-05-31
A16: loanid | B16: 7727000088 | C16: 7727000672 | D16: 7727004200 | E16: 7727000065 | F16: 7727000010
A17: group | B17: REO | C17: FCL | D17: FCL | E17: REO | F17: D120P
A18: servicer | B18: Newrez | C18: Newrez | D18: Newrez | E18: Newrez | F18: Newrez
A19: state | B19: FL | C19: MI | D19: IL | E19: FL | F19: FL
A20: judicial | B20: Y | C20: N | D20: Y | E20: Y | F20: Y
A21: demand_start_date | B21: 2025-02-18 | C21: 2025-11-17 | D21: 2025-05-20 | E21: 2024-08-12 | F21: 2026-04-10
A22: demand_end_date | B22: 2025-03-25 | C22: 2025-12-22 | D22: 2025-06-24 | E22: 2024-09-18 | F22: 2026-05-15
A23: demand_stage_days | B23: 464 | C23: 193 | D23: 333 | E23: 431 | F23: 54
A24: demand_in_lm_days | B24: — | C24: 93 | D24: 197 | E24: — | F24: —
A25: demand_on_hold_days | B25: — | C25: 17 | D25: — | E25: — | F25: —
... A62: stage | B62: JUDGEMENT | C62: SALE | D62: SALE | E62: JUDGEMENT | F62: DEMAND

Sheet ⑪ mid·portfunding
A1: port.portfunding — 融资池表（入库 JOIN 过滤；1 行/贷款）
A2: 全 57 字段 · 取数口径：当前态(1行/贷款) · 命中 5/5 贷款（无行的贷款列显示 —） · prod 实测 2026-06-04 · 业务日 2026-06-01
A3: 查询 SQL（prod 只读）： -- port.portfunding · redshift_prod(只读) · 当前态 1 行/贷款 · 业务日 2026-06-01 SELECT * FROM port.portfunding WHERE loanid IN ('7727000088','7727000672','7727004200','7727000065','7727000010') ORDER BY loanid;
A4: 📋 业务含义与全链路血缘 〔自动生成·勿手改本块；改 outputs/fcl_table_meta.json 后重跑〕
A5: 业务含义/目的：融资池表(57 列，1 行/贷款)——funding/deal 标识(fundingid/dealid)与池属性。 作为 JOIN 维度为 FCL 输出补 funding_id/bid_id，并做入库过滤。
A6: 何时来查：查某贷款属于哪个融资池/deal，或为何被 sync 过滤进/出。
A7: 为什么这样处理：BPS 需按 funding/bid 维展示与归集；FCL 表本身不含，运行时 JOIN portfunding 补齐(dealid→bid_id, fundingid→funding_id)。
A8: 数据粒度：1 行/贷款（当前态）。
A9: 上游链路：投资/融资域(非 servicer FCL 文件) → port.portfunding
A10: 全部上游表：投资/融资域来源（非 FCL servicer 文件）
A11: 下游链路：portfunding ⋈ { port.fcl_stage_info / GEN_FORECLOSURE(asset_managment_config.py:535-608) } → bpms.sync_fcl_stage_info / bpms.sync_loan_foreclosure → 视图 → BPS
A12: 全部下游表：port.fcl_stage_info、bpms.sync_fcl_stage_info、bpms.sync_loan_foreclosure、bpms.biz_data_view_loan_details_foreclosure
A13: ▲ 以上为「业务含义与全链路血缘」说明块；下方为原始数据 ────
A14: 字段 | B14: 7727000088 | C14: 7727000672 | D14: 7727004200 | E14: 7727000065 | F14: 7727000010
A15: fundingid | B15: HMP002 | C15: IMPAC001 | D15: BOA002 | E15: HMP002 | F15: HMP002
A16: dealid | B16: HMP002 | C16: IMPAC001 | D16: BOA002 | E16: HMP002 | F16: HMP002
A17: cutoffdate | B17: 2023-01-25 | C17: 2023-07-05 | D17: 2024-06-01 | E17: 2023-01-25 | F17: 2023-01-25
A18: settledate | B18: 2023-01-31 | C18: 2023-07-18 | D18: 2024-06-26 | E18: 2023-01-31 | F18: 2023-01-31
A19: wal | B19: 8.03 | C19: 8.06 | D19: 5.66 | E19: 8.03 | F19: 8.03
A20: hurdlespread | B20: 415 | C20: 408 | D20: 332 | E20: 415 | F20: 415
A21: hurdleyield | B21: 7.57 | C21: 7.54 | D21: 7.36 | E21: 7.57 | F21: 7.57
A22: loanid | B22: 7727000088 | C22: 7727000672 | D22: 7727004200 | E22: 7727000065 | F22: 7727000010
A23: sellerloanid | B23: 9010021155 | C23: 3111022026 | D23: 3260057082 | E23: 9014327961 | F23: 9014059868
A24: interestbearingupb | B24: 324035.29 | C24: 423410.11 | D24: 449829.52 | E24: 479480.42 | F24: 277928.4
A25: deferredprin | B25: 0 | C25: 0 | D25: 14062.83 | E25: 0 | F25: 0
... A71: pool | B71: A | C71: A | D71: A | E71: A | F71: A

Sheet ⑫ mid·hold
A1: port.basic_data_loan_foreclosure_hold — Redshift Hold 历史（sync_loan_foreclosure_hold 上游）
A2: 全 17 字段 · 多行/贷款（全历史） · 共 21 行 · 各贷款行数：{'7727000065': 4, '7727000088': 9, '7727000672': 2, '7727004200': 6} · prod 实测 2026-06-04
A3: 查询 SQL（prod 只读）： -- port.basic_data_loan_foreclosure_hold · redshift_prod(只读) · 多行/贷款（全历史） · 业务日 2026-06-01 SELECT * FROM port.basic_data_loan_foreclosure_hold WHERE loanid IN ('7727000088','7727000672','7727004200','7727000065','7727000010') ORDER BY loanid, fctrdt;
A4: 📋 业务含义与全链路血缘 〔自动生成·勿手改本块；改 outputs/fcl_table_meta.json 后重跑〕
A5: 业务含义/目的：Redshift Hold 历史(长表，1 行/Hold)——把源表 4 个 Hold 槽(fchold1..4)拆成长格式；Carrington 多 Hold 先排名压进 4 槽。 bpms.sync_loan_foreclosure_hold(BPS Hold 全历史)的上游；支撑‘一笔法拍多个 Hold’。
A6: 何时来查：查某贷款全部 Hold 的起止/原因/历史。
A7: 为什么这样处理：源表把 Hold 压成 4 个宽槽，业务要全历史，需拆槽(unpivot)成 1 行/Hold；一笔 FCL 多 Hold 是常态(非数据错误)。
A8: 数据粒度：1 行/贷款/Hold 段。
A9: 上游链路：newrez.portnewrezfc(fchold1..4) → port.basic_data_loan_fcl → port.basic_data_loan_foreclosure_hold〔拆槽 basic_data_pool_config.py:466-768；Carrington 排名 :504-629〕
A10: 全部上游表：newrez.portnewrezfc、port.basic_data_loan_fcl
A11: 下游链路：→ bpms.sync_loan_foreclosure_hold〔GEN_FORECLOSURE_HOLD asset_managment_config.py:847-894〕 → 视图 → BPS Hold 面板
A12: 全部下游表：bpms.sync_loan_foreclosure_hold、bpms.biz_data_view_loan_details_foreclosure
A13: ▲ 以上为「业务含义与全链路血缘」说明块；下方为原始数据 ────
A14: dataasof | B14: servicer | C14: loanid | D14: svcloanid | E14: fctrdt | F14: description1 | G14: description1_start_date | H14: description1_end_date | I14: description2 | J14: description2_start_date | K14: description2_end_date | L14: description3 | M14: description3_start_date | N14: description3_end_date | O14: description4 | P14: description4_start_date | Q14: description4_end_date
A15: 2025-05-05 | B15: Newrez | C15: 7727000065 | D15: 1031718621 | E15: 2025-05-05 | F15: Original Note | G15: 2025-02-06 | H15: 2025-03-10 | I15: — | J15: — | K15: — | L15: — | M15: — | N15: — | O15: — | P15: — | Q15: —
A16: 2025-07-02 | B16: Newrez | C16: 7727000065 | D16: 1031718621 | E16: 2025-07-02 | F16: Bankruptcy Filed | G16: 2025-05-06 | H16: 2025-06-27 | I16: Original Note | J16: 2025-02-06 | K16: 2025-03-10 | L16: — | M16: — | N16: — | O16: — | P16: — | Q16: —
A17: 2025-08-26 | B17: Newrez | C17: 7727000065 | D17: 1031718621 | E17: 2025-08-26 | F17: Court Delay | G17: 2025-07-02 | H17: 2025-07-14 | I17: Bankruptcy Filed | J17: 2025-05-06 | K17: 2025-06-27 | L17: Original Note | M17: 2025-02-06 | N17: 2025-03-10 | O17: — | P17: — | Q17: —
A18: 2026-06-04 | B18: Newrez | C18: 7727000065 | D18: 1031718621 | E18: 2026-06-04 | F18: Court Delay | G18: 2025-08-26 | H18: 2025-08-28 | I18: Court Delay | J18: 2025-07-02 | K18: 2025-07-14 | L18: Bankruptcy Filed | M18: 2025-05-06 | N18: 2025-06-27 | O18: — | P18: — | Q18: —
A19: 2025-07-15 | B19: Newrez | C19: 7727000088 | D19: 1031718838 | E19: 2025-07-15 | F19: Original Note | G19: 2025-05-28 | H19: 2025-06-11 | I19: — | J19: — | K19: — | L19: — | M19: — | N19: — | O19: — | P19: — | Q19: —
A20: 2025-07-30 | B20: Newrez | C20: 7727000088 | D20: 1031718838 | E20: 2025-07-30 | F20: Service Delay | G20: 2025-07-15 | H20: — | I20: Original Note | J20: 2025-05-28 | K20: 2025-06-11 | L20: — | M20: — | N20: — | O20: — | P20: — | Q20: —
A21: 2025-08-12 | B21: Newrez | C21: 7727000088 | D21: 1031718838 | E21: 2025-08-12 | F21: Loss Mitigation Workout | G21: 2025-07-31 | H21: 2025-08-01 | I21: Service Delay | J21: 2025-07-15 | K21: 2025-07-31 | L21: Original Note | M21: 2025-05-28 | N21: 2025-06-11 | O21: — | P21: — | Q21: —
A22: 2025-10-21 | B22: Newrez | C22: 7727000088 | D22: 1031718838 | E22: 2025-10-21 | F22: Loss Mitigation Workout | G22: 2025-08-13 | H22: 2025-10-21 | I22: Loss Mitigation Workout | J22: 2025-07-31 | K22: 2025-08-01 | L22: Service Delay | M22: 2025-07-15 | N22: 2025-07-31 | O22: — | P22: — | Q22: —
A23: 2026-01-18 | B23: Newrez | C23: 7727000088 | D23: 1031718838 | E23: 2026-01-18 | F23: Court Delay | G23: 2025-10-21 | H23: 2025-12-16 | I23: Loss Mitigation Workout | J23: 2025-08-13 | K23: 2025-10-21 | L23: Loss Mitigation Workout | M23: 2025-07-31 | N23: 2025-08-01 | O23: — | P23: — | Q23: —
A24: 2026-02-23 | B24: Newrez | C24: 7727000088 | D24: 1031718838 | E24: 2026-02-23 | F24: Loss Mitigation Workout | G24: 2026-02-20 | H24: — | I24: Court Delay | J24: 2026-01-16 | K24: — | L24: Court Delay | M24: 2025-10-21 | N24: 2025-12-16 | O24: — | P24: — | Q24: —
A25: 2026-03-16 | B25: Newrez | C25: 7727000088 | D25: 1031718838 | E25: 2026-03-16 | F25: Court Delay | G25: 2026-01-16 | H25: — | I25: Loss Mitigation Workout | J25: 2026-02-20 | K25: 2026-02-24 | L25: Court Delay | M25: 2025-10-21 | N25: 2025-12-16 | O25: — | P25: — | Q25: —
... A35: 2026-06-04 | B35: Newrez | C35: 7727004200 | D35: 0688132141 | E35: 2026-06-04 | F35: Delinquency Review | G35: 2026-04-17 | H35: 2026-04-17 | I35: Hearing Set | J35: 2026-01-29 | K35: 2026-02-13 | L35: Service Delay | M35: 2025-12-30 | N35: 2026-01-23 | O35: — | P35: — | Q35: —

Sheet ⑬ mid·loss_mitigation
A1: port.basic_data_loan_foreclosure_loss_mitigation — Redshift LM 历史（上游）
A2: 全 16 字段 · 多行/贷款（全历史） · 共 21 行 · 各贷款行数：{'7727000010': 2, '7727000065': 2, '7727000088': 9, '7727000672': 2, '7727004200': 6} · prod 实测 2026-06-04
A3: 查询 SQL（prod 只读）： -- port.basic_data_loan_foreclosure_loss_mitigation · redshift_prod(只读) · 多行/贷款（全历史） · 业务日 2026-06-01 SELECT * FROM port.basic_data_loan_foreclosure_loss_mitigation WHERE loanid IN ('7727000088','7727000672','7727004200','7727000065','7727000010') ORDER BY loanid, fctrdt;
A4: 📋 业务含义与全链路血缘 〔自动生成·勿手改本块；改 outputs/fcl_table_meta.json 后重跑〕
A5: 业务含义/目的：Redshift LM 历史(1 行/LM 周期)——按 (loanid, dealstartdate)，datadic 解码 lmdeal/lmprogram/lmstatus/lmdecision。 bpms.sync_loan_foreclosure_loss_mitigation 的上游；支撑‘一笔贷款多 LM 周期’。
A6: 何时来查：查某贷款全部 LM 周期/项目/决定(已解码)。
A7: 为什么这样处理：LM 多周期是常态；编码需经 datadic 解码成业务文案(JOIN key 拼 code+'.0')。
A8: 数据粒度：1 行/贷款/LM 周期。
A9: 上游链路：{ newrez.portnewrezlm + newrez.portnewrezdatadic } → port.basic_data_loan_fcl 体系 → port.basic_data_loan_foreclosure_loss_mitigation〔basic_data_pool_config.py:799-843〕
A10: 全部上游表：newrez.portnewrezlm、newrez.portnewrezdatadic、port.basic_data_loan_fcl
A11: 下游链路：→ bpms.sync_loan_foreclosure_loss_mitigation〔asset_managment_config.py:799-819〕 → 视图 → BPS LM 面板
A12: 全部下游表：bpms.sync_loan_foreclosure_loss_mitigation、bpms.biz_data_view_loan_details_foreclosure
A13: ▲ 以上为「业务含义与全链路血缘」说明块；下方为原始数据 ────
A14: dataasof | B14: servicer | C14: loanid | D14: svcloanid | E14: fctrdt | F14: deal | G14: program | H14: lmc_status | I14: cycle_opened_date | J14: cycle_closed_date | K14: final_disposition | L14: improgram | M14: denialreason | N14: borrower_intentions | O14: imminent_default | P14: single_point_of_contact
A15: 2026-04-15 | B15: Newrez | C15: 7727000010 | D15: 1031718692 | E15: 2026-04-15 | F15: Evaluation | G15: Evaluation | H15: Pending Financials | I15: 2024-11-26 | J15: 2024-12-23 | K15: Request Incomplete/Failed to Provide Information | L15: 21.0 | M15: — | N15: — | O15: — | P15: —
A16: 2026-06-04 | B16: Newrez | C16: 7727000010 | D16: 1031718692 | E16: 2026-06-04 | F16: Modification | G16: 498.0 | H16: Workout Denial | I16: 2026-04-16 | J16: 2026-04-28 | K16: Referral to FC | L16: 498.0 | M16: Hardship not resolved | N16: — | O16: — | P16: —
A17: 2025-06-30 | B17: Newrez | C17: 7727000065 | D17: 1031718621 | E17: 2025-06-30 | F17: Evaluation | G17: Evaluation | H17: Pending Financials | I17: 2024-11-26 | J17: 2024-12-23 | K17: Request Incomplete/Failed to Provide Information | L17: 21.0 | M17: — | N17: — | O17: — | P17: —
A18: 2026-06-04 | B18: Newrez | C18: 7727000065 | D18: 1031718621 | E18: 2026-06-04 | F18: Evaluation | G18: Evaluation | H18: Pending Financials | I18: 2025-07-01 | J18: 2025-07-01 | K18: LMS Opened in Error | L18: 21.0 | M18: — | N18: — | O18: — | P18: —
A19: 2025-01-29 | B19: Newrez | C19: 7727000088 | D19: 1031718838 | E19: 2025-01-29 | F19: Evaluation | G19: Evaluation | H19: Pending Financials | I19: 2024-09-20 | J19: 2024-10-21 | K19: Request Incomplete/Failed to Provide Information | L19: 21.0 | M19: — | N19: — | O19: — | P19: —
A20: 2025-03-16 | B20: Newrez | C20: 7727000088 | D20: 1031718838 | E20: 2025-03-16 | F20: Modification | G20: Bridger mod | H20: Workout Denial | I20: 2025-01-30 | J20: 2025-03-11 | K20: Referral to FC | L20: 419.0 | M20: — | N20: — | O20: — | P20: —
A21: 2025-05-07 | B21: Newrez | C21: 7727000088 | D21: 1031718838 | E21: 2025-05-07 | F21: Modification | G21: Bridger mod | H21: Workout Denial | I21: 2025-03-17 | J21: 2025-04-29 | K21: Referral to FC | L21: 419.0 | M21: Request Incomplete/Failed to Provide Documentation | N21: — | O21: — | P21: —
A22: 2025-06-19 | B22: Newrez | C22: 7727000088 | D22: 1031718838 | E22: 2025-06-19 | F22: Modification | G22: Bridger mod | H22: Workout Denial | I22: 2025-05-08 | J22: 2025-06-14 | K22: Referral to FC | L22: 419.0 | M22: Request Incomplete/Failed to Provide Documentation | N22: — | O22: — | P22: —
A23: 2025-10-20 | B23: Newrez | C23: 7727000088 | D23: 1031718838 | E23: 2025-10-20 | F23: Modification | G23: 496.0 | H23: Workout Denial | I23: 2025-06-20 | J23: 2025-10-20 | K23: Referral to FC | L23: 496.0 | M23: — | N23: — | O23: — | P23: —
A24: 2025-12-09 | B24: Newrez | C24: 7727000088 | D24: 1031718838 | E24: 2025-12-09 | F24: Short Sale | G24: Short Sale | H24: Document Follow-up | I24: 2025-10-20 | J24: 2025-11-21 | K24: Request Incomplete/Failed to Provide Information | L24: 8.0 | M24: — | N24: — | O24: — | P24: —
A25: 2026-01-27 | B25: Newrez | C25: 7727000088 | D25: 1031718838 | E25: 2026-01-27 | F25: DIL | G25: Deed-in-Lieu | H25: DIL Title Ordered | I25: 2025-12-10 | J25: 2026-01-27 | K25: LMS Opened in Error | L25: 10.0 | M25: — | N25: — | O25: — | P25: —
... A35: 2026-06-04 | B35: Newrez | C35: 7727004200 | D35: 0688132141 | E35: 2026-06-04 | F35: Modification | G35: 496.0 | H35: Document Follow-up | I35: 2026-01-06 | J35: 2026-02-02 | K35: Request Incomplete/Failed to Provide Information | L35: 496.0 | M35: — | N35: — | O35: — | P35: —

Sheet ⑭ mid·bankruptcy
A1: port.basic_data_loan_foreclosure_bankruptcy — Redshift 破产历史（上游）
A2: 全 15 字段 · 多行/贷款（全历史） · 共 3 行 · 各贷款行数：{'7727000010': 2, '7727000065': 1} · prod 实测 2026-06-04
A3: 查询 SQL（prod 只读）： -- port.basic_data_loan_foreclosure_bankruptcy · redshift_prod(只读) · 多行/贷款（全历史） · 业务日 2026-06-01 SELECT * FROM port.basic_data_loan_foreclosure_bankruptcy WHERE loanid IN ('7727000088','7727000672','7727004200','7727000065','7727000010') ORDER BY loanid, fctrdt;
A4: 📋 业务含义与全链路血缘 〔自动生成·勿手改本块；改 outputs/fcl_table_meta.json 后重跑〕
A5: 业务含义/目的：Redshift 破产历史(1 行/破产申请)——datadic 解码 bkstatus；Carrington 专有 mfr_filed_date(Newrez 为 NULL)。 bpms.sync_loan_foreclosure_bankruptcy 的上游。
A6: 何时来查：查某贷款全部破产申请/章节/状态(已解码)。
A7: 为什么这样处理：破产可多次申请；编码经 datadic 解码。
A8: 数据粒度：1 行/贷款/破产申请。
A9: 上游链路：{ newrez.portnewrezbk + newrez.portnewrezdatadic } → port.basic_data_loan_foreclosure_bankruptcy〔basic_data_pool_config.py:331-370〕
A10: 全部上游表：newrez.portnewrezbk、newrez.portnewrezdatadic、port.basic_data_loan_fcl
A11: 下游链路：→ bpms.sync_loan_foreclosure_bankruptcy〔asset_managment_config.py:822-843〕 → 视图 → BPS 破产面板
A12: 全部下游表：bpms.sync_loan_foreclosure_bankruptcy、bpms.biz_data_view_loan_details_foreclosure
A13: ▲ 以上为「业务含义与全链路血缘」说明块；下方为原始数据 ────
A14: dataasof | B14: servicer | C14: loanid | D14: svcloanid | E14: fctrdt | F14: bankruptcy_status | G14: legal_status | H14: status_date | I14: chapter | J14: lien_status | K14: mfr_status | L14: mfr_filed_date | M14: claim_status | N14: proof_of_claim_date | O14: post_petition_due_date
A15: 2024-07-24 | B15: Newrez | C15: 7727000010 | D15: 1031718692 | E15: 2024-07-24 | F15: Active | G15: BK13 | H15: 2023-08-23 | I15: 13 | J15: — | K15: — | L15: — | M15: — | N15: 2023-09-30 | O15: 2023-09-01
A16: 2026-06-04 | B16: Newrez | C16: 7727000010 | D16: 1031718692 | E16: 2026-06-04 | F16: Active | G16: BK13 | H16: 2024-02-06 | I16: 13 | J16: — | K16: — | L16: — | M16: — | N16: 2023-09-30 | O16: 2026-06-01
A17: 2026-06-04 | B17: Newrez | C17: 7727000065 | D17: 1031718621 | E17: 2026-06-04 | F17: Discharged | G17: REO | H17: 2025-04-30 | I17: 7 | J17: — | K17: — | L17: — | M17: — | N17: — | O17: —

Sheet ⑮ mid·temp_basic_data_fcl
A1: tempfc.temp_basic_data_fcl — Redshift 改名临时表（portnewrezfc 等原始列→统一列；运行时中间产物，basic_data_loan_fcl 的上游）
A2: 全 37 字段 · 取数口径：dataasof=MAX(每贷款) · 命中 5/5 贷款（无行的贷款列显示 —） · prod 实测 2026-06-04 · 业务日 2026-06-01
A3: 查询 SQL（prod 只读）： -- tempfc.temp_basic_data_fcl · redshift_prod(只读) · 每贷款 dataasof=MAX(最新快照) · 业务日 2026-06-01 SELECT t.* FROM tempfc.temp_basic_data_fcl t JOIN (SELECT loanid, MAX(dataasof) AS _md FROM tempfc.temp_basic_data_fcl WHERE loanid IN ('7727000088','7727000672','7727004200','7727000065','7727000010') GROUP BY loanid) m ON t.loanid=m.loanid AND t.dataasof=m._md;
A4: 📋 业务含义与全链路血缘 〔自动生成·勿手改本块；改 outputs/fcl_table_meta.json 后重跑〕
A5: 业务含义/目的：Redshift 运行时改名临时表(37 列)——把各 servicer 原始列(如 fcreferraldate)改成统一列(referral_start_date)的中间产物。 port.basic_data_loan_fcl 的直接上游；承接‘改名’这一步。
A6: 何时来查：排查‘统一列名 ↔ 源列名’映射、定位改名是否正确。
A7: 为什么这样处理：UNION 前必须先统一列名；单列一张临时表做改名，逻辑清晰、便于调试；运行时产物。
A8: 数据粒度：1 行/贷款/dataasof。
A9: 上游链路：newrez.portnewrezfc(各家源) → tempfc.temp_basic_data_fcl〔改名 basic_data_pool_config.py ~:1538-1565〕
A10: 全部上游表：newrez.portnewrezfc、Servicer 文件(L0)
A11: 下游链路：→ port.basic_data_loan_fcl(UNION) → FCL 业务族(foreclosure/stage/hold/lm/bk) → bpms.sync_* → BPS
A12: 全部下游表：port.basic_data_loan_fcl、port.basic_data_loan_foreclosure、port.fcl_stage_info、port.basic_data_loan_foreclosure_hold、port.basic_data_loan_foreclosure_loss_mitigation、port.basic_data_loan_foreclosure_bankruptcy
A13: ▲ 以上为「业务含义与全链路血缘」说明块；下方为原始数据 ────
A14: 字段 | B14: 7727000088 | C14: 7727000672 | D14: 7727004200 | E14: 7727000065 | F14: 7727000010
A15: dataasof | B15: 2026-06-04 | C15: 2026-06-04 | D15: 2026-06-04 | E15: 2026-06-04 | F15: 2026-06-04
A16: loanid | B16: 7727000088 | C16: 7727000672 | D16: 7727004200 | E16: 7727000065 | F16: 7727000010
A17: servicer | B17: Newrez | C17: Newrez | D17: Newrez | E17: Newrez | F17: Newrez
A18: svc_loanid | B18: 1031718838 | C18: 1032761570 | D18: 0688132141 | E18: 1031718621 | F18: 1031718692
A19: activefcflag | B19: 0 | C19: 0 | D19: 0 | E19: 0 | F19: 0
A20: titleordereddate | B20: — | C20: — | D20: — | E20: 2025-11-13 | F20: —
A21: titlereceiveddate | B21: — | C21: — | D21: — | E21: 2025-12-02 | F21: —
A22: titlecleardate | B22: — | C22: — | D22: — | E22: — | F22: —
A23: noi_date | B23: — | C23: — | D23: — | E23: — | F23: —
A24: fcsetupdate | B24: 2025-05-23 | C24: 2026-03-09 | D24: 2025-06-27 | E24: 2025-02-03 | F24: —
A25: referral_start_date | B25: 2025-05-23 | C25: 2026-03-09 | D25: 2025-06-27 | E25: 2025-02-03 | F25: —
... A51: activejnrlienfcflag | B51: 0 | C51: 0 | D51: 0 | E51: 0 | F51: 0

Sheet ⑯ mid·daily_loan_common
A1: port.basic_data_daily_loan_common — 逾期支线 L2 统一日表（delq_status；每贷款最新 asofdate）
A2: 全 78 字段 · 取数口径：asofdate=MAX(每贷款) · 命中 5/5 贷款（无行的贷款列显示 —） · prod 实测 2026-06-04 · 业务日 2026-06-01
A3: 查询 SQL（prod 只读）： -- port.basic_data_daily_loan_common · redshift_prod(只读) · 每贷款 asofdate=MAX(最新快照) · 业务日 2026-06-01 SELECT t.* FROM port.basic_data_daily_loan_common t JOIN (SELECT loanid, MAX(asofdate) AS _md FROM port.basic_data_daily_loan_common WHERE loanid IN ('7727000088','7727000672','7727004200','7727000065','7727000010') GROUP BY loanid) m ON t.loanid=m.loanid AND t.asofdate=m._md;
A4: 📋 业务含义与全链路血缘 〔自动生成·勿手改本块；改 outputs/fcl_table_meta.json 后重跑〕
A5: 业务含义/目的：逾期支线 L2 统一日表(78 列)——全 servicer UNION 后的标准日表，含 delq_status、fcl_flag、lm_flag 等(asofdate)。 逾期/状态归一的统一入口；L3 清洗的上游。
A6: 何时来查：查‘统一后的每日逾期/状态原值’、对账各家归一。
A7: 为什么这样处理：各家逾期/状态字段名与取值不同，先 UNION 成统一日表；注意 fcl_flag 在此并未真正归一(Newrez/SLS 为 NULL)，真正归一在 L4 FCL 业务族。
A8: 数据粒度：1 行/贷款/asofdate。
A9: 上游链路：Servicer 文件(L0) → newrez.portnewrezgeneral(等各家) → port.portdaily_v2〔portdaily_config.py〕 → port.basic_data_daily_loan_common〔daily_data_loan_common_config.py〕
A10: 全部上游表：Servicer 文件(L0)、newrez.portnewrezgeneral、newrez.portnewrezfc、port.portdaily_v2
A11: 下游链路：→ port.basic_data_daily_loan_common_clean(L3) → { port.portmonthbase / port.basic_data_fcl_related.delq_status / port.fcl_stage_info.group } → BPS
A12: 全部下游表：port.basic_data_daily_loan_common_clean、port.basic_data_fcl_related、port.fcl_stage_info、port.portmonthbase
... A14: ▲ 以上为「业务含义与全链路血缘」说明块；下方为原始数据 ────
A15: 字段 | B15: 7727000088 | C15: 7727000672 | D15: 7727004200 | E15: 7727000065 | F15: 7727000010
A16: asofdate | B16: 2026-06-04 | C16: 2026-06-04 | D16: 2026-06-04 | E16: 2026-06-04 | F16: 2026-06-04
A17: loanid | B17: 7727000088 | C17: 7727000672 | D17: 7727004200 | E17: 7727000065 | F17: 7727000010
A18: svcloanid | B18: 1031718838 | C18: 1032761570 | D18: 0688132141 | E18: 1031718621 | F18: 1031718692
A19: servicer | B19: Newrez | C19: Newrez | D19: Newrez | E19: Newrez | F19: Newrez
A20: nextduedate | B20: 2025-01-01 | C20: 2026-02-01 | D20: 2024-12-01 | E20: 2024-03-01 | F20: 2026-04-01
A21: principalbalance | B21: 316909.28 | C21: 416163.45 | D21: 0 | E21: 470399.51 | F21: 259917
A22: deferredprincipalbalance | B22: 0 | C22: 0 | D22: 0 | E22: 0 | F22: 0
A23: deferredinterestbalance | B23: 0 | C23: 0 | D23: 0 | E23: 0 | F23: 0
A24: schedule_pandi_daily | B24: 2080.37 | C24: 3690.48 | D24: 2195.33 | E24: 2381.97 | F24: 1287.59
A25: principalpaidmtd | B25: 0 | C25: 0 | D25: 0 | E25: 0 | F25: 1498.21
A26: interestpaidmtd | B26: 0 | C26: 0 | D26: 0 | E26: 0 | F26: 2364.56
... A93: balloonterm | B93: — | C93: — | D93: — | E93: — | F93: —

Sheet ⑰ mid·daily_loan_common_clean
A1: port.basic_data_daily_loan_common_clean — 逾期支线 L3 清洗日表（delinq / days360；每贷款最新 fctrdt）
A2: 全 103 字段 · 取数口径：fctrdt=MAX(每贷款) · 命中 5/5 贷款（无行的贷款列显示 —） · prod 实测 2026-06-04 · 业务日 2026-06-01
A3: 查询 SQL（prod 只读）： -- port.basic_data_daily_loan_common_clean · redshift_prod(只读) · 每贷款 fctrdt=MAX(最新快照) · 业务日 2026-06-01 SELECT t.* FROM port.basic_data_daily_loan_common_clean t JOIN (SELECT loanid, MAX(fctrdt) AS _md FROM port.basic_data_daily_loan_common_clean WHERE loanid IN ('7727000088','7727000672','7727004200','7727000065','7727000010') GROUP BY loanid) m ON t.loanid=m.loanid AND t.fctrdt=m._md;
A4: 📋 业务含义与全链路血缘 〔自动生成·勿手改本块；改 outputs/fcl_table_meta.json 后重跑〕
A5: 业务含义/目的：逾期支线 L3 清洗日表(103 列)——把 delq_status 经 CASE 归一成标准 delinq 码(C/D30/D60/D90/D120P/FCL/REO/P)，并用 days360(nextduedate,fctrdt) 分桶(fctrdt)。 标准逾期码的单一来源；喂 portmonthbase 与 FCL 业务族(stage 分组)。
A6: 何时来查：查‘标准化后的逾期码/天数桶口径’、核对 days360 计算。
A7: 为什么这样处理：业务要统一的 MBA 逾期码；文本状态(Foreclosure*/REO/Paid*)直接映射，其余按 days360 天数分桶。注意：FCL 码只来自 servicer 显式法拍状态，绝不由 days360 推导。
A8: 数据粒度：1 行/贷款/fctrdt。
A9: 上游链路：… → port.basic_data_daily_loan_common → port.basic_data_daily_loan_common_clean〔daily_data_loan_common_clean_config.py，CASE + days360〕
A10: 全部上游表：port.basic_data_daily_loan_common、port.portdaily_v2、newrez.portnewrezgeneral
A11: 下游链路：→ { port.portmonthbase / port.basic_data_fcl_related.delq_status / port.fcl_stage_info.group } → BPS。另：旁支 port.basic_data_loan_delinq_clean(含 is_ghost_payoff 等)实测存在，但其生成代码不在 PrefectFlow 仓库(grep 0 命中，开放问题)。
A12: 全部下游表：port.basic_data_fcl_related、port.fcl_stage_info、port.portmonthbase
... A14: ▲ 以上为「业务含义与全链路血缘」说明块；下方为原始数据 ────
A15: 字段 | B15: 7727000088 | C15: 7727000672 | D15: 7727004200 | E15: 7727000065 | F15: 7727000010
A16: fctrdt | B16: 2026-07-01 | C16: 2026-07-01 | D16: 2026-07-01 | E16: 2026-07-01 | F16: 2026-07-01
A17: dealid | B17: HMP002 | C17: IMPAC001 | D17: BOA002 | E17: HMP002 | F17: HMP002
A18: fundingid | B18: HMP002 | C18: IMPAC001 | D18: BOA002 | E18: HMP002 | F18: HMP002
A19: loanid | B19: 7727000088 | C19: 7727000672 | D19: 7727004200 | E19: 7727000065 | F19: 7727000010
A20: svcloanid | B20: 1031718838 | C20: 1032761570 | D20: 0688132141 | E20: 1031718621 | F20: 1031718692
A21: servicer | B21: Newrez | C21: Newrez | D21: Newrez | E21: Newrez | F21: Newrez
A22: agency | B22: Conventional | C22: Conventional | D22: Conventional | E22: VA | F22: VA
A23: channel | B23: broker | C23: broker | D23: retail | E23: broker | F23: retail
A24: purpose | B24: Purchase | C24: Purchase | D24: Purchase | E24: Refinance-Cash | F24: Refinance-Cash
A25: proptype | B25: SingleFamilyDetached | C25: SingleFamilyDetached | D25: PUD | E25: SingleFamilyDetached | F25: SingleFamilyDetached
A26: occupancy | B26: Vacant | C26: Owner Occupied | D26: Owner Occupied | E26: Vacant | F26: Owner Occupied
... A118: reasonfordefault | B118: Reduction in Borrower's Income | C118: — | D118: — | E118: Unable to Contact Borrower | F118: —

Sheet ⑱ bps·sync_loan_foreclosure
A1: bpms.sync_loan_foreclosure — Summary/Timeline/target 主表
A2: 全 72 字段 · 取数口径：当前态(1行/贷款) · 命中 4/5 贷款（无行的贷款列显示 —） · prod 实测 2026-06-04 · 业务日 2026-06-01 ⚠️ mapping 验证发现（取数公式 vs 实际 BPS，2026-06-04；prod 覆盖式刷新口径）：① summary_current_step 实际=fcstage ≠ 文档 COALESCE(currentmilestone, fcstage)，待 ETL 代码核实（doc 13 Q13）；② 多个字段在主表未填充（Newrez 源有值/BPS 空）：timeline_notice_of_intent(_end)/approved_for_referral/referred_to_attorney/foreclosure_completed、summary_servicer_number/summary_completed_foreclosure/summary_foreclosure_attorney（同源 summary_firm 却有值＝部分填充，doc 13 Q14）。红色「取数公式」格 = 公式≠实际。
A3: 查询 SQL（prod 只读）： -- bpms.sync_loan_foreclosure · mysql_prod(只读) · 当前态 1 行/贷款 · 业务日 2026-06-01 SELECT * FROM bpms.sync_loan_foreclosure WHERE loanid IN (7727000088,7727000672,7727004200,7727000065,7727000010) ORDER BY loanid;
A4: 📋 业务含义与全链路血缘 〔自动生成·勿手改本块；改 outputs/fcl_table_meta.json 后重跑〕
A5: 业务含义/目的：BPS 法拍主表(72 列，当前态)——Summary/Timeline/target 主面板的数据源。 BPS 直接对接表；法拍主面板。
A6: 何时来查：查 BPS 主面板某字段的落库值、排查面板与 Redshift 是否一致。
A7: 为什么这样处理：L4 算好后同步到 MySQL 供 BPS 读；采用覆盖更新(coverage upsert)，并对天数做 NY 当日实时校正(+DATEDIFF)。
A8: 数据粒度：1 行/贷款（过滤 timeline_referred… IS NOT NULL，即已进入法拍）。
A9: 上游链路：… → port.basic_data_loan_foreclosure(Redshift) → (sync_to_mysql/update_to_mysql df_db_util.py:665-726) → bpms.sync_loan_foreclosure〔GEN_FORECLOSURE asset_managment_config.py:535-608〕（JOIN port.portfunding 取 funding_id/bid_id）
A10: 全部上游表：port.basic_data_loan_foreclosure、port.portfunding、port.basic_data_loan_fcl
A11: 下游链路：→ bpms.biz_data_view_loan_details_foreclosure(视图) → BPS 法拍详情/主面板
A12: 全部下游表：bpms.biz_data_view_loan_details_foreclosure
... A14: ▲ 以上为「业务含义与全链路血缘」说明块；下方为原始数据 ────
A15: 字段 | B15: src(Newrez)→BPS 映射规则 (doc 13/16) | C15: 7727000088 | D15: 7727000088 取数公式 | E15: 7727000672 | F15: 7727000672 取数公式 | G15: 7727004200 | H15: 7727004200 取数公式 | I15: 7727000065 | J15: 7727000065 取数公式 | K15: 7727000010 | L15: 7727000010 取数公式
A16: id | B16: BPS 内部生成/审计字段 | C16: 217 | D16: — 注：BPS 内部生成/审计字段 | E16: 530 | F16: — 注：BPS 内部生成/审计字段 | G16: 257 | H16: — 注：BPS 内部生成/审计字段 | I16: 82 | J16: — 注：BPS 内部生成/审计字段 | K16: — | L16: — 注：BPS 内部生成/审计字段
A17: bid_id | B17: BPS 内部生成/审计字段 | C17: HMP002 | D17: — 注：BPS 内部生成/审计字段 | E17: IMPAC001 | F17: — 注：BPS 内部生成/审计字段 | G17: BOA002 | H17: — 注：BPS 内部生成/审计字段 | I17: HMP002 | J17: — 注：BPS 内部生成/审计字段 | K17: — | L17: — 注：BPS 内部生成/审计字段
A18: funding_id | B18: BPS 内部生成/审计字段 | C18: HMP002 | D18: — 注：BPS 内部生成/审计字段 | E18: IMPAC001 | F18: — 注：BPS 内部生成/审计字段 | G18: BOA002 | H18: — 注：BPS 内部生成/审计字段 | I18: HMP002 | J18: — 注：BPS 内部生成/审计字段 | K18: — | L18: — 注：BPS 内部生成/审计字段
A19: loanid | B19: 直接取值：portnewrezfc.loanid | C19: 7727000088 | D19: ='② src·portnewrezfc'!B6 | E19: 7727000672 | F19: ='② src·portnewrezfc'!C6 | G19: 7727004200 | H19: ='② src·portnewrezfc'!D6 | I19: 7727000065 | J19: ='② src·portnewrezfc'!E6 | K19: — | L19: ='② src·portnewrezfc'!F6
A20: svcloanid | B20: 直接取值：portnewrezfc.shellpointloanid | C20: 1031718838 | D20: ='② src·portnewrezfc'!B8 | E20: 1032761570 | F20: ='② src·portnewrezfc'!C8 | G20: 0688132141 | H20: ='② src·portnewrezfc'!D8 | I20: 1031718621 | J20: ='② src·portnewrezfc'!E8 | K20: — | L20: ='② src·portnewrezfc'!F8
A21: servicer | B21: 固定值 'Newrez' | C21: Newrez | D21: ="Newrez" | E21: Newrez | F21: ="Newrez" | G21: Newrez | H21: ="Newrez" | I21: Newrez | J21: ="Newrez" | K21: — | L21: ="Newrez"
A22: timeline_notice_of_intent_date | B22: 直接取值：portnewrezfc.demandsentdate | C22: — | D22: ='② src·portnewrezfc'!B13 | E22: — | F22: ='② src·portnewrezfc'!C13 | G22: — | H22: ='② src·portnewrezfc'!D13 | I22: — | J22: ='② src·portnewrezfc'!E13 | K22: — | L22: ='② src·portnewrezfc'!F13
A23: timeline_notice_of_intent_end_date | B23: 直接取值：portnewrezfc.demandexpirationdate | C23: — | D23: ='② src·portnewrezfc'!B14 | E23: — | F23: ='② src·portnewrezfc'!C14 | G23: — | H23: ='② src·portnewrezfc'!D14 | I23: — | J23: ='② src·portnewrezfc'!E14 | K23: — | L23: ='② src·portnewrezfc'!F14
A24: timeline_approved_for_referral_date | B24: 直接取值：portnewrezfc.fcsetupdate | C24: — | D24: ='② src·portnewrezfc'!B9 | E24: — | F24: ='② src·portnewrezfc'!C9 | G24: — | H24: ='② src·portnewrezfc'!D9 | I24: — | J24: ='② src·portnewrezfc'!E9 | K24: — | L24: ='② src·portnewrezfc'!F9
A25: timeline_referred_to_attorney_date | B25: 直接取值：portnewrezfc.fcreferraldate | C25: — | D25: ='② src·portnewrezfc'!B10 | E25: — | F25: ='② src·portnewrezfc'!C10 | G25: — | H25: ='② src·portnewrezfc'!D10 | I25: — | J25: ='② src·portnewrezfc'!E10 | K25: — | L25: ='② src·portnewrezfc'!F10
A26: timeline_referred_to_foreclosure_date | B26: 直接取值：portnewrezfc.fcreferraldate | C26: 2025-05-23 | D26: ='② src·portnewrezfc'!B10 | E26: 2026-03-09 | F26: ='② src·portnewrezfc'!C10 | G26: 2025-06-27 | H26: ='② src·portnewrezfc'!D10 | I26: 2025-02-03 | J26: ='② src·portnewrezfc'!E10 | K26: — | L26: ='② src·portnewrezfc'!F10
A27: timeline_title_report_received_date | B27: 直接取值：portnewrezfc.titlereceiveddate | C27: — | D27: ='② src·portnewrezfc'!B34 | E27: — | F27: ='② src·portnewrezfc'!C34 | G27: — | H27: ='② src·portnewrezfc'!D34 | I27: 2025-12-02 | J27: ='② src·portnewrezfc'!E34 | K27: — | L27: ='② src·portnewrezfc'!F34
A28: timeline_preliminary_title_cleared_date | B28: 直接取值：portnewrezfc.titlecleardate | C28: — | D28: ='② src·portnewrezfc'!B33 | E28: — | F28: ='② src·portnewrezfc'!C33 | G28: — | H28: ='② src·portnewrezfc'!D33 | I28: — | J28: ='② src·portnewrezfc'!E33 | K28: — | L28: ='② src·portnewrezfc'!F33
A29: timeline_first_legal_date | B29: 直接取值：portnewrezfc.firstlegaldate | C29: 2025-06-13 | D29: ='② src·portnewrezfc'!B30 | E29: 2026-03-25 | F29: ='② src·portnewrezfc'!C30 | G29: 2025-07-21 | H29: ='② src·portnewrezfc'!D30 | I29: 2025-03-27 | J29: ='② src·portnewrezfc'!E30 | K29: — | L29: ='② src·portnewrezfc'!F30
A30: timeline_service_date | B30: 直接取值：portnewrezfc.servicecompletedate | C30: 2025-07-18 | D30: ='② src·portnewrezfc'!B31 | E30: — | F30: ='② src·portnewrezfc'!C31 | G30: 2025-12-24 | H30: ='② src·portnewrezfc'!D31 | I30: 2025-05-03 | J30: ='② src·portnewrezfc'!E31 | K30: — | L30: ='② src·portnewrezfc'!F31
A31: timeline_publication_date | B31: Newrez 未提供，恒空 | C31: — | D31: — 注：Newrez 未提供，恒空 | E31: — | F31: — 注：Newrez 未提供，恒空 | G31: — | H31: — 注：Newrez 未提供，恒空 | I31: — | J31: — 注：Newrez 未提供，恒空 | K31: — | L31: — 注：Newrez 未提供，恒空
A32: timeline_judgement_hearing_set_date | B32: ETL 跨快照 MIN(dataasof WHERE 值=当前)，单快照不可复现 | C32: 2025-12-17 | D32: — 注：ETL 跨快照 MIN(dataasof WHERE 值=当前)，单快照不可复现 | E32: — | F32: — 注：ETL 跨快照 MIN(dataasof WHERE 值=当前)，单快照不可复现 | G32: 2026-02-13 | H32: — 注：ETL 跨快照 MIN(dataasof WHERE 值=当前)，单快照不可复现 | I32: 2025-07-15 | J32: — 注：ETL 跨快照 MIN(dataasof WHERE 值=当前)，单快照不可复现 | K32: — | L32: — 注：ETL 跨快照 MIN(dataasof WHERE 值=当前)，单快照不可复现
A33: timeline_judgement_date | B33: 直接取值：portnewrezfc.fcjudgmenthearingscheduled | C33: 2026-03-27 | D33: ='② src·portnewrezfc'!B24 | E33: — | F33: ='② src·portnewrezfc'!C24 | G33: 2026-04-13 | H33: ='② src·portnewrezfc'!D24 | I33: 2025-10-15 | J33: ='② src·portnewrezfc'!E24 | K33: — | L33: ='② src·portnewrezfc'!F24
A34: timeline_sale_date_projected_date | B34: 直接取值：portnewrezfc.fcscheduledsaledate | C34: — | D34: ='② src·portnewrezfc'!B26 | E34: — | F34: ='② src·portnewrezfc'!C26 | G34: 2026-05-19 | H34: ='② src·portnewrezfc'!D26 | I34: — | J34: ='② src·portnewrezfc'!E26 | K34: — | L34: ='② src·portnewrezfc'!F26
A35: timeline_sale_date_set_date | B35: ETL 跨快照 MIN(dataasof WHERE 值=当前)，单快照不可复现 | C35: — | D35: — 注：ETL 跨快照 MIN(dataasof WHERE 值=当前)，单快照不可复现 | E35: — | F35: — 注：ETL 跨快照 MIN(dataasof WHERE 值=当前)，单快照不可复现 | G35: 2026-02-19 | H35: — 注：ETL 跨快照 MIN(dataasof WHERE 值=当前)，单快照不可复现 | I35: — | J35: — 注：ETL 跨快照 MIN(dataasof WHERE 值=当前)，单快照不可复现 | K35: — | L35: — 注：ETL 跨快照 MIN(dataasof WHERE 值=当前)，单快照不可复现
A36: timeline_final_title_cleared_date | B36: 直接取值：portnewrezfc.titlecleardate | C36: — | D36: ='② src·portnewrezfc'!B33 | E36: — | F36: ='② src·portnewrezfc'!C33 | G36: — | H36: ='② src·portnewrezfc'!D33 | I36: — | J36: ='② src·portnewrezfc'!E33 | K36: — | L36: ='② src·portnewrezfc'!F33
A37: timeline_sale_date_held_date | B37: 直接取值：portnewrezfc.fcsalehelddate | C37: 2026-05-22 | D37: ='② src·portnewrezfc'!B27 | E37: — | F37: ='② src·portnewrezfc'!C27 | G37: — | H37: ='② src·portnewrezfc'!D27 | I37: 2025-10-14 | J37: ='② src·portnewrezfc'!E27 | K37: — | L37: ='② src·portnewrezfc'!F27
A38: timeline_foreclosure_completed_date | B38: COALESCE(dtdeedrecorded, fcremovaldate) | C38: — | D38: =IF('② src·portnewrezfc'!B51<>"—",'② src·portnewrezfc'!B51,'② src·portnewrezfc'!B36) | E38: — | F38: =IF('② src·portnewrezfc'!C51<>"—",'② src·portnewrezfc'!C51,'② src·portnewrezfc'!C36) | G38: — | H38: =IF('② src·portnewrezfc'!D51<>"—",'② src·portnewrezfc'!D51,'② src·portnewrezfc'!D36) | I38: — | J38: =IF('② src·portnewrezfc'!E51<>"—",'② src·portnewrezfc'!E51,'② src·portnewrezfc'!E36) | K38: — | L38: =IF('② src·portnewrezfc'!F51<>"—",'② src·portnewrezfc'!F51,'② src·portnewrezfc'!F36)
A39: timeline_third_party_sold_date_date | B39: fcresults='3rd Party' 时取 fcsalehelddate，否则空 | C39: — | D39: =IF('② src·portnewrezfc'!B29="3rd Party",'② src·portnewrezfc'!B27,"") | E39: — | F39: =IF('② src·portnewrezfc'!C29="3rd Party",'② src·portnewrezfc'!C27,"") | G39: — | H39: =IF('② src·portnewrezfc'!D29="3rd Party",'② src·portnewrezfc'!D27,"") | I39: — | J39: =IF('② src·portnewrezfc'!E29="3rd Party",'② src·portnewrezfc'!E27,"") | K39: — | L39: =IF('② src·portnewrezfc'!F29="3rd Party",'② src·portnewrezfc'!F27,"")
A40: timeline_third_party_proceeds_received_date | B40: 直接取值：portnewrezfc.fcl3rdpartyproceedsreceiveddate | C40: — | D40: ='② src·portnewrezfc'!B53 | E40: — | F40: ='② src·portnewrezfc'!C53 | G40: — | H40: ='② src·portnewrezfc'!D53 | I40: — | J40: ='② src·portnewrezfc'!E53 | K40: — | L40: ='② src·portnewrezfc'!F53
A41: target_notice_of_intent_days | B41: 系统配置常量（state/judicial/servicer 预设，与 Newrez 无关） | C41: 30 | D41: — 注：系统配置常量（state/judicial/servicer 预设，与 Newrez 无关） | E41: 30 | F41: — 注：系统配置常量（state/judicial/servicer 预设，与 Newrez 无关） | G41: 30 | H41: — 注：系统配置常量（state/judicial/servicer 预设，与 Newrez 无关） | I41: 30 | J41: — 注：系统配置常量（state/judicial/servicer 预设，与 Newrez 无关） | K41: — | L41: — 注：系统配置常量（state/judicial/servicer 预设，与 Newrez 无关）
A42: target_notice_of_intent_expired_days | B42: 系统配置常量（state/judicial/servicer 预设，与 Newrez 无关） | C42: 90 | D42: — 注：系统配置常量（state/judicial/servicer 预设，与 Newrez 无关） | E42: 90 | F42: — 注：系统配置常量（state/judicial/servicer 预设，与 Newrez 无关） | G42: 90 | H42: — 注：系统配置常量（state/judicial/servicer 预设，与 Newrez 无关） | I42: 90 | J42: — 注：系统配置常量（state/judicial/servicer 预设，与 Newrez 无关） | K42: — | L42: — 注：系统配置常量（state/judicial/servicer 预设，与 Newrez 无关）
A43: target_approved_for_referral_days | B43: 系统配置常量（state/judicial/servicer 预设，与 Newrez 无关） | C43: 30 | D43: — 注：系统配置常量（state/judicial/servicer 预设，与 Newrez 无关） | E43: 30 | F43: — 注：系统配置常量（state/judicial/servicer 预设，与 Newrez 无关） | G43: 30 | H43: — 注：系统配置常量（state/judicial/servicer 预设，与 Newrez 无关） | I43: 30 | J43: — 注：系统配置常量（state/judicial/servicer 预设，与 Newrez 无关） | K43: — | L43: — 注：系统配置常量（state/judicial/servicer 预设，与 Newrez 无关）
A44: target_referred_to_attorney_days | B44: 系统配置常量（state/judicial/servicer 预设，与 Newrez 无关） | C44: 1 | D44: — 注：系统配置常量（state/judicial/servicer 预设，与 Newrez 无关） | E44: 1 | F44: — 注：系统配置常量（state/judicial/servicer 预设，与 Newrez 无关） | G44: 1 | H44: — 注：系统配置常量（state/judicial/servicer 预设，与 Newrez 无关） | I44: 1 | J44: — 注：系统配置常量（state/judicial/servicer 预设，与 Newrez 无关） | K44: — | L44: — 注：系统配置常量（state/judicial/servicer 预设，与 Newrez 无关）
A45: target_referred_to_foreclosure_days | B45: 系统配置常量（state/judicial/servicer 预设，与 Newrez 无关） | C45: 1 | D45: — 注：系统配置常量（state/judicial/servicer 预设，与 Newrez 无关） | E45: 1 | F45: — 注：系统配置常量（state/judicial/servicer 预设，与 Newrez 无关） | G45: 1 | H45: — 注：系统配置常量（state/judicial/servicer 预设，与 Newrez 无关） | I45: 1 | J45: — 注：系统配置常量（state/judicial/servicer 预设，与 Newrez 无关） | K45: — | L45: — 注：系统配置常量（state/judicial/servicer 预设，与 Newrez 无关）
A46: target_title_report_received_days | B46: 系统配置常量（state/judicial/servicer 预设，与 Newrez 无关） | C46: 30 | D46: — 注：系统配置常量（state/judicial/servicer 预设，与 Newrez 无关） | E46: 30 | F46: — 注：系统配置常量（state/judicial/servicer 预设，与 Newrez 无关） | G46: 30 | H46: — 注：系统配置常量（state/judicial/servicer 预设，与 Newrez 无关） | I46: 30 | J46: — 注：系统配置常量（state/judicial/servicer 预设，与 Newrez 无关） | K46: — | L46: — 注：系统配置常量（state/judicial/servicer 预设，与 Newrez 无关）
A47: target_preliminary_title_cleared_days | B47: 系统配置常量（state/judicial/servicer 预设，与 Newrez 无关） | C47: 30 | D47: — 注：系统配置常量（state/judicial/servicer 预设，与 Newrez 无关） | E47: 30 | F47: — 注：系统配置常量（state/judicial/servicer 预设，与 Newrez 无关） | G47: 30 | H47: — 注：系统配置常量（state/judicial/servicer 预设，与 Newrez 无关） | I47: 30 | J47: — 注：系统配置常量（state/judicial/servicer 预设，与 Newrez 无关） | K47: — | L47: — 注：系统配置常量（state/judicial/servicer 预设，与 Newrez 无关）
A48: target_first_legal_days | B48: 系统配置常量（state/judicial/servicer 预设，与 Newrez 无关） | C48: 120 | D48: — 注：系统配置常量（state/judicial/servicer 预设，与 Newrez 无关） | E48: 120 | F48: — 注：系统配置常量（state/judicial/servicer 预设，与 Newrez 无关） | G48: 120 | H48: — 注：系统配置常量（state/judicial/servicer 预设，与 Newrez 无关） | I48: 120 | J48: — 注：系统配置常量（state/judicial/servicer 预设，与 Newrez 无关） | K48: — | L48: — 注：系统配置常量（state/judicial/servicer 预设，与 Newrez 无关）
A49: target_service_days | B49: 系统配置常量（state/judicial/servicer 预设，与 Newrez 无关） | C49: 90 | D49: — 注：系统配置常量（state/judicial/servicer 预设，与 Newrez 无关） | E49: 90 | F49: — 注：系统配置常量（state/judicial/servicer 预设，与 Newrez 无关） | G49: 90 | H49: — 注：系统配置常量（state/judicial/servicer 预设，与 Newrez 无关） | I49: 90 | J49: — 注：系统配置常量（state/judicial/servicer 预设，与 Newrez 无关） | K49: — | L49: — 注：系统配置常量（state/judicial/servicer 预设，与 Newrez 无关）
A50: target_publication_days | B50: 系统配置常量（state/judicial/servicer 预设，与 Newrez 无关） | C50: 30 | D50: — 注：系统配置常量（state/judicial/servicer 预设，与 Newrez 无关） | E50: 30 | F50: — 注：系统配置常量（state/judicial/servicer 预设，与 Newrez 无关） | G50: 30 | H50: — 注：系统配置常量（state/judicial/servicer 预设，与 Newrez 无关） | I50: 30 | J50: — 注：系统配置常量（state/judicial/servicer 预设，与 Newrez 无关） | K50: — | L50: — 注：系统配置常量（state/judicial/servicer 预设，与 Newrez 无关）
A51: target_judgement_hearing_set_days | B51: 系统配置常量（state/judicial/servicer 预设，与 Newrez 无关） | C51: 120 | D51: — 注：系统配置常量（state/judicial/servicer 预设，与 Newrez 无关） | E51: 120 | F51: — 注：系统配置常量（state/judicial/servicer 预设，与 Newrez 无关） | G51: 120 | H51: — 注：系统配置常量（state/judicial/servicer 预设，与 Newrez 无关） | I51: 120 | J51: — 注：系统配置常量（state/judicial/servicer 预设，与 Newrez 无关） | K51: — | L51: — 注：系统配置常量（state/judicial/servicer 预设，与 Newrez 无关）
A52: target_judgement_days | B52: 系统配置常量（state/judicial/servicer 预设，与 Newrez 无关） | C52: 30 | D52: — 注：系统配置常量（state/judicial/servicer 预设，与 Newrez 无关） | E52: 30 | F52: — 注：系统配置常量（state/judicial/servicer 预设，与 Newrez 无关） | G52: 30 | H52: — 注：系统配置常量（state/judicial/servicer 预设，与 Newrez 无关） | I52: 30 | J52: — 注：系统配置常量（state/judicial/servicer 预设，与 Newrez 无关） | K52: — | L52: — 注：系统配置常量（state/judicial/servicer 预设，与 Newrez 无关）
... A60: bid_approval_status | B60: BPS 内部工作流字段（非 Newrez） | C60: — | D60: — 注：BPS 内部工作流字段（非 Newrez） | E60: — | F60: — 注：BPS 内部工作流字段（非 Newrez） | G60: — | H60: — 注：BPS 内部工作流字段（非 Newrez） | I60: — | J60: — 注：BPS 内部工作流字段（非 Newrez） | K60: — | L60: — 注：BPS 内部工作流字段（非 Newrez）
A61: bid_approval_sale_date | B61: 直接取值：portnewrezfc.fcscheduledsaledate | C61: — | D61: ='② src·portnewrezfc'!B26 | E61: — | F61: ='② src·portnewrezfc'!C26 | G61: — | H61: ='② src·portnewrezfc'!D26 | I61: — | J61: ='② src·portnewrezfc'!E26 | K61: — | L61: ='② src·portnewrezfc'!F26
A62: bid_approval_bid_amount | B62: 直接取值：portnewrezfc.fcapprbidprice | C62: 301500 | D62: ='② src·portnewrezfc'!B52 | E62: — | F62: ='② src·portnewrezfc'!C52 | G62: — | H62: ='② src·portnewrezfc'!D52 | I62: 390832.5 | J62: ='② src·portnewrezfc'!E52 | K62: — | L62: ='② src·portnewrezfc'!F52
A63: bid_approval_loan_resolution_holods | B63: BPS 拼接 fchold1/2/3description | C63: — | D63: — 注：BPS 拼接 fchold1/2/3description | E63: — | F63: — 注：BPS 拼接 fchold1/2/3description | G63: — | H63: — 注：BPS 拼接 fchold1/2/3description | I63: — | J63: — 注：BPS 拼接 fchold1/2/3description | K63: — | L63: — 注：BPS 拼接 fchold1/2/3description
A64: summary_servicer_number | B64: 直接取值：portnewrezfc.shellpointloanid | C64: — | D64: ='② src·portnewrezfc'!B8 | E64: — | F64: ='② src·portnewrezfc'!C8 | G64: — | H64: ='② src·portnewrezfc'!D8 | I64: — | J64: ='② src·portnewrezfc'!E8 | K64: — | L64: ='② src·portnewrezfc'!F8
A65: summary_foreclosure_status | B65: activefcflag=1→'Active Foreclosure'；=0 且 fcremovaldesc 非空→'Closed Foreclosure:'+fcremovaldesc；否则 NULL | C65: Closed Foreclosure:Process Complete | D65: =IF('② src·portnewrezfc'!B42="1","Active Foreclosure",IF(AND('② src·portnewrezfc'!B42="0",'② src·portnewrezfc'!B35<>"—"),"Closed Foreclosure:"&'② src·portnewrezfc'!B35,"")) | E65: Closed Foreclosure:Loss Mitigation | F65: =IF('② src·portnewrezfc'!C42="1","Active Foreclosure",IF(AND('② src·portnewrezfc'!C42="0",'② src·portnewrezfc'!C35<>"—"),"Closed Foreclosure:"&'② src·portnewrezfc'!C35,"")) | G65: Closed Foreclosure:Paid in Full | H65: =IF('② src·portnewrezfc'!D42="1","Active Foreclosure",IF(AND('② src·portnewrezfc'!D42="0",'② src·portnewrezfc'!D35<>"—"),"Closed Foreclosure:"&'② src·portnewrezfc'!D35,"")) | I65: Closed Foreclosure:Process Complete | J65: =IF('② src·portnewrezfc'!E42="1","Active Foreclosure",IF(AND('② src·portnewrezfc'!E42="0",'② src·portnewrezfc'!E35<>"—"),"Closed Foreclosure:"&'② src·portnewrezfc'!E35,"")) | K65: — | L65: =IF('② src·portnewrezfc'!F42="1","Active Foreclosure",IF(AND('② src·portnewrezfc'!F42="0",'② src·portnewrezfc'!F35<>"—"),"Closed Foreclosure:"&'② src·portnewrezfc'!F35,""))
A66: summary_completed_foreclosure | B66: activefcflag 取反：=0→1，=1→0（prod 实测该列全 NULL） | C66: — | D66: =IF('② src·portnewrezfc'!B42="0","1",IF('② src·portnewrezfc'!B42="1","0","")) | E66: — | F66: =IF('② src·portnewrezfc'!C42="0","1",IF('② src·portnewrezfc'!C42="1","0","")) | G66: — | H66: =IF('② src·portnewrezfc'!D42="0","1",IF('② src·portnewrezfc'!D42="1","0","")) | I66: — | J66: =IF('② src·portnewrezfc'!E42="0","1",IF('② src·portnewrezfc'!E42="1","0","")) | K66: — | L66: =IF('② src·portnewrezfc'!F42="0","1",IF('② src·portnewrezfc'!F42="1","0",""))
A67: summary_foreclosure_bid_amount | B67: 直接取值：portnewrezfc.fcbidamount | C67: 301500 | D67: ='② src·portnewrezfc'!B41 | E67: — | F67: ='② src·portnewrezfc'!C41 | G67: — | H67: ='② src·portnewrezfc'!D41 | I67: 390832.5 | J67: ='② src·portnewrezfc'!E41 | K67: — | L67: ='② src·portnewrezfc'!F41
A68: summary_srv_fc_bid_amount | B68: 直接取值：portnewrezfc.fcbidamount | C68: 301500 | D68: ='② src·portnewrezfc'!B41 | E68: — | F68: ='② src·portnewrezfc'!C41 | G68: — | H68: ='② src·portnewrezfc'!D41 | I68: 390832.5 | J68: ='② src·portnewrezfc'!E41 | K68: — | L68: ='② src·portnewrezfc'!F41
A69: summary_foreclosure_sale_amount | B69: 直接取值：portnewrezfc.fcsaleamount | C69: 200100 | D69: ='② src·portnewrezfc'!B28 | E69: — | F69: ='② src·portnewrezfc'!C28 | G69: — | H69: ='② src·portnewrezfc'!D28 | I69: 357200 | J69: ='② src·portnewrezfc'!E28 | K69: — | L69: ='② src·portnewrezfc'!F28
A70: summary_judicial_foreclosure | B70: 直接取值：portnewrezfc.judicial | C70: 1 | D70: ='② src·portnewrezfc'!B38 | E70: 0 | F70: ='② src·portnewrezfc'!C38 | G70: 1 | H70: ='② src·portnewrezfc'!D38 | I70: 1 | J70: ='② src·portnewrezfc'!E38 | K70: — | L70: ='② src·portnewrezfc'!F38
A71: summary_foreclosure_attorney | B71: 直接取值：portnewrezfc.fcfirm | C71: — | D71: ='② src·portnewrezfc'!B39 | E71: — | F71: ='② src·portnewrezfc'!C39 | G71: — | H71: ='② src·portnewrezfc'!D39 | I71: — | J71: ='② src·portnewrezfc'!E39 | K71: — | L71: ='② src·portnewrezfc'!F39
A72: summary_contested_litigation | B72: 直接取值：portnewrezfc.fccontestedflag | C72: 0 | D72: ='② src·portnewrezfc'!B37 | E72: 0 | F72: ='② src·portnewrezfc'!C37 | G72: 0 | H72: ='② src·portnewrezfc'!D37 | I72: 0 | J72: ='② src·portnewrezfc'!E37 | K72: — | L72: ='② src·portnewrezfc'!F37
A73: summary_firm | B73: 直接取值：portnewrezfc.fcfirm | C73: Kelley Kronenberg, P.A. | D73: ='② src·portnewrezfc'!B39 | E73: Orlans Law Group PLLC | F73: ='② src·portnewrezfc'!C39 | G73: Johnson, Blumberg & Associates, LLC | H73: ='② src·portnewrezfc'!D39 | I73: RAS (Primary) | J73: ='② src·portnewrezfc'!E39 | K73: — | L73: ='② src·portnewrezfc'!F39
A74: summary_type | B74: judicial=1→'Judicial'；=0→'Non Judicial'；NULL→NULL | C74: Judicial | D74: =IF('② src·portnewrezfc'!B38="1","Judicial",IF('② src·portnewrezfc'!B38="0","Non Judicial","")) | E74: Non Judicial | F74: =IF('② src·portnewrezfc'!C38="1","Judicial",IF('② src·portnewrezfc'!C38="0","Non Judicial","")) | G74: Judicial | H74: =IF('② src·portnewrezfc'!D38="1","Judicial",IF('② src·portnewrezfc'!D38="0","Non Judicial","")) | I74: Judicial | J74: =IF('② src·portnewrezfc'!E38="1","Judicial",IF('② src·portnewrezfc'!E38="0","Non Judicial","")) | K74: — | L74: =IF('② src·portnewrezfc'!F38="1","Judicial",IF('② src·portnewrezfc'!F38="0","Non Judicial",""))
A75: summary_sms_days_in_fcl | B75: 原值 smsdaysinfc + DATEDIFF(今日纽约, dataasof) 实时重算（≈BPS 载入时点） | C75: 370 | D75: =IF('② src·portnewrezfc'!B11="—","—",'② src·portnewrezfc'!B11+(TODAY()-DATEVALUE('② src·portnewrezfc'!B7))) | E75: 81 | F75: =IF('② src·portnewrezfc'!C11="—","—",'② src·portnewrezfc'!C11+(TODAY()-DATEVALUE('② src·portnewrezfc'!C7))) | G75: 296 | H75: =IF('② src·portnewrezfc'!D11="—","—",'② src·portnewrezfc'!D11+(TODAY()-DATEVALUE('② src·portnewrezfc'!D7))) | I75: 256 | J75: =IF('② src·portnewrezfc'!E11="—","—",'② src·portnewrezfc'!E11+(TODAY()-DATEVALUE('② src·portnewrezfc'!E7))) | K75: — | L75: =IF('② src·portnewrezfc'!F11="—","—",'② src·portnewrezfc'!F11+(TODAY()-DATEVALUE('② src·portnewrezfc'!F7)))
A76: summary_days_in_fcl | B76: 原值 daysinfc + DATEDIFF(今日纽约, dataasof) 实时重算（≈BPS 载入时点） | C76: 370 | D76: =IF('② src·portnewrezfc'!B12="—","—",'② src·portnewrezfc'!B12+(TODAY()-DATEVALUE('② src·portnewrezfc'!B7))) | E76: 81 | F76: =IF('② src·portnewrezfc'!C12="—","—",'② src·portnewrezfc'!C12+(TODAY()-DATEVALUE('② src·portnewrezfc'!C7))) | G76: 296 | H76: =IF('② src·portnewrezfc'!D12="—","—",'② src·portnewrezfc'!D12+(TODAY()-DATEVALUE('② src·portnewrezfc'!D7))) | I76: 256 | J76: =IF('② src·portnewrezfc'!E12="—","—",'② src·portnewrezfc'!E12+(TODAY()-DATEVALUE('② src·portnewrezfc'!E7))) | K76: — | L76: =IF('② src·portnewrezfc'!F12="—","—",'② src·portnewrezfc'!F12+(TODAY()-DATEVALUE('② src·portnewrezfc'!F7)))
A77: summary_current_step | B77: COALESCE(currentmilestone, fcstage) | C77: Post Sale Review (SCRA and PACER Check) | D77: =IF('② src·portnewrezfc'!B62<>"—",'② src·portnewrezfc'!B62,'② src·portnewrezfc'!B15) | E77: Pre-Sale Review 1 (SCRA and PACER Check) | F77: =IF('② src·portnewrezfc'!C62<>"—",'② src·portnewrezfc'!C62,'② src·portnewrezfc'!C15) | G77: Pre-Sale Review 1 (SCRA and PACER Check) | H77: =IF('② src·portnewrezfc'!D62<>"—",'② src·portnewrezfc'!D62,'② src·portnewrezfc'!D15) | I77: Post Sale Review (SCRA and PACER Check) | J77: =IF('② src·portnewrezfc'!E62<>"—",'② src·portnewrezfc'!E62,'② src·portnewrezfc'!E15) | K77: — | L77: =IF('② src·portnewrezfc'!F62<>"—",'② src·portnewrezfc'!F62,'② src·portnewrezfc'!F15)
A78: summary_last_step_completed | B78: 直接取值：portnewrezfc.lastfcstepcompleted | C78: Post Sale Review (SCRA and PACER Check) | D78: ='② src·portnewrezfc'!B16 | E78: First Publication | F78: ='② src·portnewrezfc'!C16 | G78: Sale Scheduled For | H78: ='② src·portnewrezfc'!D16 | I78: Post Sale Review (SCRA and PACER Check) | J78: ='② src·portnewrezfc'!E16 | K78: — | L78: ='② src·portnewrezfc'!F16
A79: summary_last_step_completed_date | B79: 直接取值：portnewrezfc.lastfcstepcompleteddate | C79: 2026-05-26 | D79: ='② src·portnewrezfc'!B17 | E79: 2026-03-25 | F79: ='② src·portnewrezfc'!C17 | G79: 2026-05-19 | H79: ='② src·portnewrezfc'!D17 | I79: 2025-10-15 | J79: ='② src·portnewrezfc'!E17 | K79: — | L79: ='② src·portnewrezfc'!F17
A80: create_user | B80: BPS 内部生成/审计字段 | C80: — | D80: — 注：BPS 内部生成/审计字段 | E80: — | F80: — 注：BPS 内部生成/审计字段 | G80: — | H80: — 注：BPS 内部生成/审计字段 | I80: — | J80: — 注：BPS 内部生成/审计字段 | K80: — | L80: — 注：BPS 内部生成/审计字段
A81: create_dept | B81: BPS 内部生成/审计字段 | C81: — | D81: — 注：BPS 内部生成/审计字段 | E81: — | F81: — 注：BPS 内部生成/审计字段 | G81: — | H81: — 注：BPS 内部生成/审计字段 | I81: — | J81: — 注：BPS 内部生成/审计字段 | K81: — | L81: — 注：BPS 内部生成/审计字段
A82: create_time | B82: BPS 内部生成/审计字段 | C82: — | D82: — 注：BPS 内部生成/审计字段 | E82: — | F82: — 注：BPS 内部生成/审计字段 | G82: — | H82: — 注：BPS 内部生成/审计字段 | I82: — | J82: — 注：BPS 内部生成/审计字段 | K82: — | L82: — 注：BPS 内部生成/审计字段
A83: update_user | B83: BPS 内部生成/审计字段 | C83: — | D83: — 注：BPS 内部生成/审计字段 | E83: — | F83: — 注：BPS 内部生成/审计字段 | G83: — | H83: — 注：BPS 内部生成/审计字段 | I83: — | J83: — 注：BPS 内部生成/审计字段 | K83: — | L83: — 注：BPS 内部生成/审计字段
A84: update_time | B84: BPS 内部生成/审计字段 | C84: — | D84: — 注：BPS 内部生成/审计字段 | E84: — | F84: — 注：BPS 内部生成/审计字段 | G84: — | H84: — 注：BPS 内部生成/审计字段 | I84: — | J84: — 注：BPS 内部生成/审计字段 | K84: — | L84: — 注：BPS 内部生成/审计字段
A85: status | B85: BPS 内部生成/审计字段 | C85: 0 | D85: — 注：BPS 内部生成/审计字段 | E85: 0 | F85: — 注：BPS 内部生成/审计字段 | G85: 0 | H85: — 注：BPS 内部生成/审计字段 | I85: 0 | J85: — 注：BPS 内部生成/审计字段 | K85: — | L85: — 注：BPS 内部生成/审计字段
A86: is_deleted | B86: BPS 内部生成/审计字段 | C86: 0 | D86: — 注：BPS 内部生成/审计字段 | E86: 0 | F86: — 注：BPS 内部生成/审计字段 | G86: 0 | H86: — 注：BPS 内部生成/审计字段 | I86: 0 | J86: — 注：BPS 内部生成/审计字段 | K86: — | L86: — 注：BPS 内部生成/审计字段
A87: tenant_id | B87: BPS 内部生成/审计字段 | C87: 000000 | D87: — 注：BPS 内部生成/审计字段 | E87: 000000 | F87: — 注：BPS 内部生成/审计字段 | G87: 000000 | H87: — 注：BPS 内部生成/审计字段 | I87: 000000 | J87: — 注：BPS 内部生成/审计字段 | K87: — | L87: — 注：BPS 内部生成/审计字段

Sheet ⑲ bps·sync_fcl_stage_info
A1: bpms.sync_fcl_stage_info — 聚合 Stage/Timeline 表
A2: 全 57 字段 · 取数口径：fctrdt=MAX(每贷款) · 命中 5/5 贷款（无行的贷款列显示 —） · prod 实测 2026-06-04 · 业务日 2026-06-01
A3: 查询 SQL（prod 只读）： -- bpms.sync_fcl_stage_info · mysql_prod(只读) · 每贷款 fctrdt=MAX(最新快照) · 业务日 2026-06-01 SELECT t.* FROM bpms.sync_fcl_stage_info t JOIN (SELECT loanid, MAX(fctrdt) AS _md FROM bpms.sync_fcl_stage_info WHERE loanid IN (7727000088,7727000672,7727004200,7727000065,7727000010) GROUP BY loanid) m ON t.loanid=m.loanid AND t.fctrdt=m._md;
A4: 📋 业务含义与全链路血缘 〔自动生成·勿手改本块；改 outputs/fcl_table_meta.json 后重跑〕
A5: 业务含义/目的：BPS 聚合 Stage/Timeline 表(57 列)——各阶段停留天数/时间线。 BPS Stage 面板数据源。
A6: 何时来查：查 BPS 各阶段天数落库值。
A7: 为什么这样处理：阶段口径在 Redshift 算清后同步；JOIN portfunding 带 funding 维。
A8: 数据粒度：1 行/贷款/fctrdt（过滤 activefcflag=1 且 fcremovaldate IS NULL）。
A9: 上游链路：port.fcl_stage_info(⋈ port.portfunding) → bpms.sync_fcl_stage_info〔GET_FCL_STAGE_DATA asset_managment_config.py:925-929〕
A10: 全部上游表：port.fcl_stage_info、port.portfunding
A11: 下游链路：→ bpms.biz_data_view_loan_details_foreclosure(视图) → BPS Stage 面板
A12: 全部下游表：bpms.biz_data_view_loan_details_foreclosure
A13: ▲ 以上为「业务含义与全链路血缘」说明块；下方为原始数据 ────
A14: 字段 | B14: 7727000088 | C14: 7727000672 | D14: 7727004200 | E14: 7727000065 | F14: 7727000010
A15: id | B15: 1550100 | C15: 1549886 | D15: 1545354 | E15: 1544054 | F15: 1548985
A16: stage | B16: JUDGEMENT | C16: SALE | D16: SALE | E16: JUDGEMENT | F16: DEMAND
A17: fctrdt | B17: 2026-05-25 | C17: 2026-05-26 | D17: 2026-04-15 | E17: 2025-10-14 | F17: 2026-05-31
A18: loanid | B18: 7727000088 | C18: 7727000672 | D18: 7727004200 | E18: 7727000065 | F18: 7727000010
A19: group | B19: REO | C19: FCL | D19: FCL | E19: REO | F19: D120P
A20: servicer | B20: Newrez | C20: Newrez | D20: Newrez | E20: Newrez | F20: Newrez
A21: state | B21: FL | C21: MI | D21: IL | E21: FL | F21: FL
A22: judicial | B22: Y | C22: N | D22: Y | E22: Y | F22: Y
A23: demand_start_date | B23: 2025-02-18 | C23: 2025-11-17 | D23: 2025-05-20 | E23: 2024-08-12 | F23: 2026-04-10
A24: demand_end_date | B24: 2025-03-25 | C24: 2025-12-22 | D24: 2025-06-24 | E24: 2024-09-18 | F24: 2026-05-15
A25: demand_stage_days | B25: 464 | C25: 193 | D25: 333 | E25: 431 | F25: 54
... A71: tenant_id | B71: 000000 | C71: 000000 | D71: 000000 | E71: 000000 | F71: 000000

Sheet ⑳ bps·view_loan_details
A1: bpms.biz_data_view_loan_details_foreclosure — 详情页视图（actual/var 天数；每贷款最新 fctrdt）
A2: 全 104 字段 · 取数口径：每贷款 fctrdt 最新一行 · 命中 5/5 贷款（无行的贷款列显示 —） · prod 实测 2026-06-04 · 业务日 2026-06-01
A3: 查询 SQL（prod 只读）： -- bpms.biz_data_view_loan_details_foreclosure · mysql_prod(只读) · 每贷款 fctrdt=MAX(最新快照) · 业务日 2026-06-01 SELECT t.* FROM bpms.biz_data_view_loan_details_foreclosure t JOIN (SELECT loanid, MAX(fctrdt) AS _md FROM bpms.biz_data_view_loan_details_foreclosure WHERE loanid IN (7727000088,7727000672,7727004200,7727000065,7727000010) GROUP BY loanid) m ON t.loanid=m.loanid AND t.fctrdt=m._md;
A4: 📋 业务含义与全链路血缘 〔自动生成·勿手改本块；改 outputs/fcl_table_meta.json 后重跑〕
A5: 业务含义/目的：BPS 法拍详情页视图(104 列)——把主表 + stage + hold + lm + bk 用 LEFT JOIN 拼成详情页；含 actual/var 天数。 BPS 详情页的‘一站式’读取视图。
A6: 何时来查：查详情页某列从哪几张 sync 表拼来、actual vs target 差异。
A7: 为什么这样处理：详情页要跨 5 张面板表聚合，用视图免去前端多次查询。
A8: 数据粒度：1 行/贷款/fctrdt（取最新）。
A9: 上游链路：{ bpms.sync_loan_foreclosure + bpms.sync_fcl_stage_info + bpms.sync_loan_foreclosure_hold + bpms.sync_loan_foreclosure_loss_mitigation + bpms.sync_loan_foreclosure_bankruptcy } → 视图(LEFT JOIN，104 列)
A10: 全部上游表：bpms.sync_loan_foreclosure、bpms.sync_fcl_stage_info、bpms.sync_loan_foreclosure_hold、bpms.sync_loan_foreclosure_loss_mitigation、bpms.sync_loan_foreclosure_bankruptcy
A11: 下游链路：→ BPS 法拍详情页 UI（5 面板）
A12: 全部下游表：BPS 法拍详情页 UI
A13: ▲ 以上为「业务含义与全链路血缘」说明块；下方为原始数据 ────
A14: 字段 | B14: 7727000088 | C14: 7727000672 | D14: 7727004200 | E14: 7727000065 | F14: 7727000010
A15: id | B15: 217 | C15: 530 | D15: 257 | E15: 82 | F15: —
A16: loanid | B16: 7727000088 | C16: 7727000672 | D16: 7727004200 | E16: 7727000065 | F16: 7727000010
A17: svcloanid | B17: 1031718838 | C17: 1032761570 | D17: 0688132141 | E17: 1031718621 | F17: 1031718692
A18: fctrdt | B18: 2026-06-01 | C18: 2026-06-01 | D18: 2026-06-01 | E18: 2026-06-01 | F18: 2026-06-01
A19: nextduedate | B19: 2025-01-01 | C19: 2026-02-01 | D19: 2024-12-01 | E19: 2024-03-01 | F19: 2026-01-01
A20: timeline_notice_of_intent_date | B20: — | C20: — | D20: — | E20: — | F20: —
A21: timeline_notice_of_intent_end_date | B21: — | C21: — | D21: — | E21: — | F21: —
A22: timeline_approved_for_referral_date | B22: — | C22: — | D22: — | E22: — | F22: —
A23: timeline_referred_to_attorney_date | B23: — | C23: — | D23: — | E23: — | F23: —
A24: timeline_referred_to_foreclosure_date | B24: 2025-05-23 | C24: 2026-03-09 | D24: 2025-06-27 | E24: 2025-02-03 | F24: —
A25: timeline_title_report_received_date | B25: — | C25: — | D25: — | E25: 2025-12-02 | F25: —
... A118: actual_total | B118: — | C118: — | D118: — | E118: — | F118: —

Sheet ㉑ bps·hold
A1: bpms.sync_loan_foreclosure_hold — Hold 全历史（每次变更一行）
A2: 全 15 字段 · 多行/贷款（全历史） · 共 21 行 · 各贷款行数：{'7727000065': 4, '7727000088': 9, '7727000672': 2, '7727004200': 6} · prod 实测 2026-06-04
A3: 查询 SQL（prod 只读）： -- bpms.sync_loan_foreclosure_hold · mysql_prod(只读) · 多行/贷款（全历史） · 业务日 2026-06-01 SELECT * FROM bpms.sync_loan_foreclosure_hold WHERE loanid IN (7727000088,7727000672,7727004200,7727000065,7727000010) ORDER BY loanid, description_start_date;
A4: 📋 业务含义与全链路血缘 〔自动生成·勿手改本块；改 outputs/fcl_table_meta.json 后重跑〕
A5: 业务含义/目的：BPS Hold 全历史(每次变更一行)。 BPS Hold 面板。
A6: 何时来查：查 BPS 上某贷款全部 Hold 落库记录。
A7: 为什么这样处理：见 ⑫；L4 拆槽后同步覆盖更新。
A8: 数据粒度：1 行/Hold 段。
A9: 上游链路：port.basic_data_loan_foreclosure_hold → bpms.sync_loan_foreclosure_hold〔asset_managment_config.py:847-894〕
A10: 全部上游表：port.basic_data_loan_foreclosure_hold
A11: 下游链路：→ bpms.biz_data_view_loan_details_foreclosure(视图) → BPS Hold 面板
A12: 全部下游表：bpms.biz_data_view_loan_details_foreclosure
A13: ▲ 以上为「业务含义与全链路血缘」说明块；下方为原始数据 ────
A14: id | B14: loanid | C14: svcloanid | D14: fctrdt | E14: description | F14: description_start_date | G14: description_end_date | H14: create_user | I14: create_dept | J14: create_time | K14: update_user | L14: update_time | M14: status | N14: is_deleted | O14: tenant_id
A15: 100379 | B15: 7727000065 | C15: 1031718621 | D15: 2025-05-05 | E15: Original Note | F15: 2025-02-06 | G15: 2025-03-10 | H15: — | I15: — | J15: — | K15: — | L15: — | M15: 0 | N15: 0 | O15: 000000
A16: 100320 | B16: 7727000065 | C16: 1031718621 | D16: 2025-07-02 | E16: Bankruptcy Filed | F16: 2025-05-06 | G16: 2025-06-27 | H16: — | I16: — | J16: — | K16: — | L16: — | M16: 0 | N16: 0 | O16: 000000
A17: 100311 | B17: 7727000065 | C17: 1031718621 | D17: 2025-08-26 | E17: Court Delay | F17: 2025-07-02 | G17: 2025-07-14 | H17: — | I17: — | J17: — | K17: — | L17: — | M17: 0 | N17: 0 | O17: 000000
A18: 100290 | B18: 7727000065 | C18: 1031718621 | D18: 2026-06-04 | E18: Court Delay | F18: 2025-08-26 | G18: 2025-08-28 | H18: — | I18: — | J18: — | K18: — | L18: — | M18: 0 | N18: 0 | O18: 000000
A19: 100325 | B19: 7727000088 | C19: 1031718838 | D19: 2025-07-15 | E19: Original Note | F19: 2025-05-28 | G19: 2025-06-11 | H19: — | I19: — | J19: — | K19: — | L19: — | M19: 0 | N19: 0 | O19: 000000
A20: 100306 | B20: 7727000088 | C20: 1031718838 | D20: 2025-07-30 | E20: Service Delay | F20: 2025-07-15 | G20: 2025-07-31 | H20: — | I20: — | J20: — | K20: — | L20: — | M20: 0 | N20: 0 | O20: 000000
A21: 100305 | B21: 7727000088 | C21: 1031718838 | D21: 2025-08-12 | E21: Loss Mitigation Workout | F21: 2025-07-31 | G21: 2025-08-01 | H21: — | I21: — | J21: — | K21: — | L21: — | M21: 0 | N21: 0 | O21: 000000
A22: 100256 | B22: 7727000088 | C22: 1031718838 | D22: 2025-10-21 | E22: Loss Mitigation Workout | F22: 2025-08-13 | G22: 2025-10-21 | H22: — | I22: — | J22: — | K22: — | L22: — | M22: 0 | N22: 0 | O22: 000000
A23: 100226 | B23: 7727000088 | C23: 1031718838 | D23: 2026-01-18 | E23: Court Delay | F23: 2025-10-21 | G23: 2025-12-16 | H23: — | I23: — | J23: — | K23: — | L23: — | M23: 0 | N23: 0 | O23: 000000
A24: 100169 | B24: 7727000088 | C24: 1031718838 | D24: 2026-02-23 | E24: Court Delay | F24: 2026-01-16 | G24: 2026-03-16 | H24: — | I24: — | J24: — | K24: — | L24: — | M24: 0 | N24: 0 | O24: 000000
A25: 100176 | B25: 7727000088 | C25: 1031718838 | D25: 2026-02-23 | E25: Loss Mitigation Workout | F25: 2026-02-20 | G25: 2026-02-24 | H25: — | I25: — | J25: — | K25: — | L25: — | M25: 0 | N25: 0 | O25: 000000
... A35: 100143 | B35: 7727004200 | C35: 0688132141 | D35: 2026-06-04 | E35: Delinquency Review | F35: 2026-04-17 | G35: 2026-04-17 | H35: — | I35: — | J35: — | K35: — | L35: — | M35: 0 | N35: 0 | O35: 000000

Sheet ㉒ bps·loss_mitigation
A1: bpms.sync_loan_foreclosure_loss_mitigation — LM 周期历史
A2: 全 22 字段 · 多行/贷款（全历史） · 共 21 行 · 各贷款行数：{'7727000010': 2, '7727000065': 2, '7727000088': 9, '7727000672': 2, '7727004200': 6} · prod 实测 2026-06-04
A3: 查询 SQL（prod 只读）： -- bpms.sync_loan_foreclosure_loss_mitigation · mysql_prod(只读) · 多行/贷款（全历史） · 业务日 2026-06-01 SELECT * FROM bpms.sync_loan_foreclosure_loss_mitigation WHERE loanid IN (7727000088,7727000672,7727004200,7727000065,7727000010) ORDER BY loanid, cycle_opened_date;
A4: 📋 业务含义与全链路血缘 〔自动生成·勿手改本块；改 outputs/fcl_table_meta.json 后重跑〕
A5: 业务含义/目的：BPS LM 周期历史(1 行/LM 周期，已解码)。 BPS LM 面板。
A6: 何时来查：查 BPS 上某贷款全部 LM 周期落库记录。
A7: 为什么这样处理：见 ⑬；L4 解码后同步覆盖更新。
A8: 数据粒度：1 行/LM 周期。
A9: 上游链路：port.basic_data_loan_foreclosure_loss_mitigation → bpms.sync_loan_foreclosure_loss_mitigation〔asset_managment_config.py:799-819〕
A10: 全部上游表：port.basic_data_loan_foreclosure_loss_mitigation
A11: 下游链路：→ bpms.biz_data_view_loan_details_foreclosure(视图) → BPS LM 面板
A12: 全部下游表：bpms.biz_data_view_loan_details_foreclosure
A13: ▲ 以上为「业务含义与全链路血缘」说明块；下方为原始数据 ────
A14: id | B14: loanid | C14: svcloanid | D14: fctrdt | E14: deal | F14: program | G14: lmc_status | H14: cycle_opened_date | I14: cycle_closed_date | J14: final_disposition | K14: denialreason | L14: borrower_intentions | M14: imminent_default | N14: single_point_of_contact | O14: create_user | P14: create_dept | Q14: create_time | R14: update_user | S14: update_time | T14: status | U14: is_deleted | V14: tenant_id
A15: 183363 | B15: 7727000010 | C15: 1031718692 | D15: 2026-04-15 | E15: Evaluation | F15: Evaluation | G15: Pending Financials | H15: 2024-11-26 | I15: 2024-12-23 | J15: Request Incomplete/Failed to Provide Information | K15: — | L15: — | M15: — | N15: — | O15: — | P15: — | Q15: — | R15: — | S15: — | T15: 0 | U15: 0 | V15: 000000
A16: 183364 | B16: 7727000010 | C16: 1031718692 | D16: 2026-06-04 | E16: Modification | F16: 498.0 | G16: Workout Denial | H16: 2026-04-16 | I16: 2026-04-28 | J16: Referral to FC | K16: Hardship not resolved | L16: — | M16: — | N16: — | O16: — | P16: — | Q16: — | R16: — | S16: — | T16: 0 | U16: 0 | V16: 000000
A17: 183370 | B17: 7727000065 | C17: 1031718621 | D17: 2025-06-30 | E17: Evaluation | F17: Evaluation | G17: Pending Financials | H17: 2024-11-26 | I17: 2024-12-23 | J17: Request Incomplete/Failed to Provide Information | K17: — | L17: — | M17: — | N17: — | O17: — | P17: — | Q17: — | R17: — | S17: — | T17: 0 | U17: 0 | V17: 000000
A18: 183371 | B18: 7727000065 | C18: 1031718621 | D18: 2026-06-04 | E18: Evaluation | F18: Evaluation | G18: Pending Financials | H18: 2025-07-01 | I18: 2025-07-01 | J18: LMS Opened in Error | K18: — | L18: — | M18: — | N18: — | O18: — | P18: — | Q18: — | R18: — | S18: — | T18: 0 | U18: 0 | V18: 000000
A19: 183380 | B19: 7727000088 | C19: 1031718838 | D19: 2025-01-29 | E19: Evaluation | F19: Evaluation | G19: Pending Financials | H19: 2024-09-20 | I19: 2024-10-21 | J19: Request Incomplete/Failed to Provide Information | K19: — | L19: — | M19: — | N19: — | O19: — | P19: — | Q19: — | R19: — | S19: — | T19: 0 | U19: 0 | V19: 000000
A20: 183381 | B20: 7727000088 | C20: 1031718838 | D20: 2025-03-16 | E20: Modification | F20: Bridger mod | G20: Workout Denial | H20: 2025-01-30 | I20: 2025-03-11 | J20: Referral to FC | K20: — | L20: — | M20: — | N20: — | O20: — | P20: — | Q20: — | R20: — | S20: — | T20: 0 | U20: 0 | V20: 000000
A21: 183382 | B21: 7727000088 | C21: 1031718838 | D21: 2025-05-07 | E21: Modification | F21: Bridger mod | G21: Workout Denial | H21: 2025-03-17 | I21: 2025-04-29 | J21: Referral to FC | K21: Request Incomplete/Failed to Provide Documentation | L21: — | M21: — | N21: — | O21: — | P21: — | Q21: — | R21: — | S21: — | T21: 0 | U21: 0 | V21: 000000
A22: 183383 | B22: 7727000088 | C22: 1031718838 | D22: 2025-06-19 | E22: Modification | F22: Bridger mod | G22: Workout Denial | H22: 2025-05-08 | I22: 2025-06-14 | J22: Referral to FC | K22: Request Incomplete/Failed to Provide Documentation | L22: — | M22: — | N22: — | O22: — | P22: — | Q22: — | R22: — | S22: — | T22: 0 | U22: 0 | V22: 000000
A23: 183384 | B23: 7727000088 | C23: 1031718838 | D23: 2025-10-20 | E23: Modification | F23: 496.0 | G23: Workout Denial | H23: 2025-06-20 | I23: 2025-10-20 | J23: Referral to FC | K23: — | L23: — | M23: — | N23: — | O23: — | P23: — | Q23: — | R23: — | S23: — | T23: 0 | U23: 0 | V23: 000000
A24: 183385 | B24: 7727000088 | C24: 1031718838 | D24: 2025-12-09 | E24: Short Sale | F24: Short Sale | G24: Document Follow-up | H24: 2025-10-20 | I24: 2025-11-21 | J24: Request Incomplete/Failed to Provide Information | K24: — | L24: — | M24: — | N24: — | O24: — | P24: — | Q24: — | R24: — | S24: — | T24: 0 | U24: 0 | V24: 000000
A25: 183386 | B25: 7727000088 | C25: 1031718838 | D25: 2026-01-27 | E25: DIL | F25: Deed-in-Lieu | G25: DIL Title Ordered | H25: 2025-12-10 | I25: 2026-01-27 | J25: LMS Opened in Error | K25: — | L25: — | M25: — | N25: — | O25: — | P25: — | Q25: — | R25: — | S25: — | T25: 0 | U25: 0 | V25: 000000
... A35: 183875 | B35: 7727004200 | C35: 0688132141 | D35: 2026-06-04 | E35: Modification | F35: 496.0 | G35: Document Follow-up | H35: 2026-01-06 | I35: 2026-02-02 | J35: Request Incomplete/Failed to Provide Information | K35: — | L35: — | M35: — | N35: — | O35: — | P35: — | Q35: — | R35: — | S35: — | T35: 0 | U35: 0 | V35: 000000

Sheet ㉓ bps·bankruptcy
A1: bpms.sync_loan_foreclosure_bankruptcy — 破产记录
A2: 全 22 字段 · 多行/贷款（全历史） · 共 3 行 · 各贷款行数：{'7727000010': 2, '7727000065': 1} · prod 实测 2026-06-04
A3: 查询 SQL（prod 只读）： -- bpms.sync_loan_foreclosure_bankruptcy · mysql_prod(只读) · 多行/贷款（全历史） · 业务日 2026-06-01 SELECT * FROM bpms.sync_loan_foreclosure_bankruptcy WHERE loanid IN (7727000088,7727000672,7727004200,7727000065,7727000010) ORDER BY loanid, status_date;
A4: 📋 业务含义与全链路血缘 〔自动生成·勿手改本块；改 outputs/fcl_table_meta.json 后重跑〕
A5: 业务含义/目的：BPS 破产记录(1 行/破产申请，已解码)。 BPS 破产面板。
A6: 何时来查：查 BPS 上某贷款全部破产记录落库值。
A7: 为什么这样处理：见 ⑭；L4 解码后同步覆盖更新。
A8: 数据粒度：1 行/破产申请。
A9: 上游链路：port.basic_data_loan_foreclosure_bankruptcy → bpms.sync_loan_foreclosure_bankruptcy〔asset_managment_config.py:822-843〕
A10: 全部上游表：port.basic_data_loan_foreclosure_bankruptcy
A11: 下游链路：→ bpms.biz_data_view_loan_details_foreclosure(视图) → BPS 破产面板
A12: 全部下游表：bpms.biz_data_view_loan_details_foreclosure
A13: ▲ 以上为「业务含义与全链路血缘」说明块；下方为原始数据 ────
A14: id | B14: loanid | C14: svcloanid | D14: fctrdt | E14: bankruptcy_status | F14: legal_status | G14: status_date | H14: chapter | I14: lien_status | J14: mfr_status | K14: mfr_filed_date | L14: claim_status | M14: proof_of_claim_date | N14: post_petition_due_date | O14: create_user | P14: create_dept | Q14: create_time | R14: update_user | S14: update_time | T14: status | U14: is_deleted | V14: tenant_id
A15: 20797 | B15: 7727000010 | C15: 1031718692 | D15: 2024-07-24 | E15: Active | F15: BK13 | G15: 2023-08-23 | H15: 13 | I15: — | J15: — | K15: — | L15: — | M15: 2023-09-30 | N15: 2023-09-01 | O15: — | P15: — | Q15: — | R15: — | S15: — | T15: 0 | U15: 0 | V15: 000000
A16: 20798 | B16: 7727000010 | C16: 1031718692 | D16: 2026-06-04 | E16: Active | F16: BK13 | G16: 2024-02-06 | H16: 13 | I16: — | J16: — | K16: — | L16: — | M16: 2023-09-30 | N16: 2026-06-01 | O16: — | P16: — | Q16: — | R16: — | S16: — | T16: 0 | U16: 0 | V16: 000000
A17: 20800 | B17: 7727000065 | C17: 1031718621 | D17: 2026-06-04 | E17: Discharged | F17: REO | G17: 2025-04-30 | H17: 7 | I17: — | J17: — | K17: — | L17: — | M17: — | N17: — | O17: — | P17: — | Q17: — | R17: — | S17: — | T17: 0 | U17: 0 | V17: 000000

Sheet ㉔ dict·portnewrezdatadic
A1: newrez.portnewrezdatadic — FCL 解码字典（仅列 5 样例贷款用到的码）
A2: 字典在 redshift_prod.newrez.portnewrezdatadic（列 package/module_name/appendix/field_name/code/description）。本表只列 5 样例贷款实际出现的码（其原始整数码见各 Newrez 源 sheet）；各字段完整字典见 docs/foreclosure_data_dictionary.md 表26。解码 JOIN：basic_data_pool_config.py:835-840(LM)/:367(BK)。prod 实测 2026-06-04。
A3: 查询 SQL（prod 只读）： -- redshift_prod.newrez.portnewrezdatadic（FCL 解码字段） SELECT field_name, code, description FROM newrez.portnewrezdatadic WHERE (module_name='LossMitigation' AND field_name IN ('LMDeal','LMProgram','LMStatus','LMDecision','DenialReason','BorrowerIntention')) OR (module_name='Bankruptcy' AND field_name IN ('BKStatus','BKStage'));
A4: LMDeal ← newrez.portnewrezlm.lmdeal（LossMitigation；字典 13 码 · prod 8 码 · 本5贷款 6 码）
A5: 编码 | B5: 解码（description） | C5: 模块
A6: 1 | B6: Modification | C6: LossMitigation
A7: 2 | B7: Evaluation | C7: LossMitigation
A8: 4 | B8: Payment Plan | C8: LossMitigation
A9: 5 | B9: Forbearance | C9: LossMitigation
A10: 6 | B10: Short Sale | C10: LossMitigation
A11: 7 | B11: DIL | C11: LossMitigation
A12: LMProgram ← newrez.portnewrezlm.lmprogram（LossMitigation；字典 388 码 · prod 22 码 · 本5贷款 9 码）
A13: 编码 | B13: 解码（description） | C13: 模块
A14: 8 | B14: Short Sale | C14: LossMitigation
A15: 10 | B15: Deed-in-Lieu | C15: LossMitigation
A16: 12 | B16: Short-term Forbearance | C16: LossMitigation
A17: 14 | B17: Unemployment Forbearance | C17: LossMitigation
A18: 21 | B18: Evaluation | C18: LossMitigation
A19: 29 | B19: Repayment Plan | C19: LossMitigation
A20: 419 | B20: Bridger mod | C20: LossMitigation
A21: 496 | B21: （字典无此码） | C21: LossMitigation
A22: 498 | B22: （字典无此码） | C22: LossMitigation
A23: LMStatus ← newrez.portnewrezlm.lmstatus（LossMitigation；字典 149 码 · prod 16 码 · 本5贷款 18 码）
A24: 编码 | B24: 解码（description） | C24: 模块
A25: 5 | B25: Document Follow-up | C25: LossMitigation
A26: 10 | B26: Underwriting Review | C26: LossMitigation
A27: 11 | B27: Underwriting Review Complete | C27: LossMitigation
A28: 13 | B28: Follow up for 1st Trial Payment | C28: LossMitigation
A29: 24 | B29: Awaiting investor approval | C29: LossMitigation
A30: 25 | B30: Monitor for pmts/funds | C30: LossMitigation
A31: 44 | B31: Submitted for Approval | C31: LossMitigation
A32: 45 | B32: Countered by Supervisor | C32: LossMitigation
A33: 48 | B33: Underwriting Follow Up Required | C33: LossMitigation
A34: 101 | B34: Resubmitted to Underwriting | C34: LossMitigation
A35: 104 | B35: Awaiting MI Approval | C35: LossMitigation
... A42: 172 | B42: Liquidation Referral | C42: LossMitigation
A43: LMDecision ← newrez.portnewrezlm.lmdecision（LossMitigation；字典 23 码 · prod 13 码 · 本5贷款 5 码）
A44: 编码 | B44: 解码（description） | C44: 模块
A45: 4 | B45: Forbearance Complete | C45: LossMitigation
A46: 6 | B46: Referral to FC | C46: LossMitigation
A47: 10 | B47: Request Incomplete/Failed to Provide Information | C47: LossMitigation
A48: 11 | B48: LMS Opened in Error | C48: LossMitigation
A49: 99 | B49: Pending | C49: LossMitigation
A50: DenialReason ← newrez.portnewrezlm.denialreason（LossMitigation；字典 130 码 · prod 19 码 · 本5贷款 6 码）
A51: 编码 | B51: 解码（description） | C51: 模块
A52: 2 | B52: Trial Plan Default | C52: LossMitigation
A53: 4 | B53: Withdrawal of Request/Non-Acceptance | C53: LossMitigation
A54: 21 | B54: Request Incomplete/Failed to Provide Documentation | C54: LossMitigation
A55: 40 | B55: PMI Company Decline | C55: LossMitigation
A56: 76 | B56: HAMP Sunset | C56: LossMitigation
A57: 124 | B57: Hardship not resolved | C57: LossMitigation
A58: BorrowerIntention ← newrez.portnewrezlm.borrowerintention（LossMitigation；字典 3 码 · prod 2 码 · 本5贷款 1 码）
A59: 编码 | B59: 解码（description） | C59: 模块
A60: 2 | B60: Retention | C60: LossMitigation
A61: BKStatus ← newrez.portnewrezbk.bkstatus（Bankruptcy；字典 5 码 · prod 5 码 · 本5贷款 4 码）
A62: 编码 | B62: 解码（description） | C62: 模块
A63: 1 | B63: Active | C63: Bankruptcy
A64: 2 | B64: Discharged | C64: Bankruptcy
A65: 4 | B65: Closed | C65: Bankruptcy
A66: 5 | B66: ReliefGranted | C66: Bankruptcy
A67: BKStage ← newrez.portnewrezbk.bkstage（Bankruptcy；字典 22 码 · prod 6 码 · 本5贷款 6 码）
A68: 📋 业务含义与全链路血缘 〔自动生成·勿手改本块；改 outputs/fcl_table_meta.json 后重跑〕
A69: 业务含义/目的：Newrez FCL 解码字典(8 列)——把 LM/BK 等编码(LMDeal/LMProgram/LMStatus/LMDecision/BKStatus 等)映射成业务文案。 给 LM/BK 等表的编码解码提供查找表。
A70: 何时来查：查某编码的业务含义、核对解码是否正确。
A71: 为什么这样处理：源表存编码省空间，展示需文案；统一一张字典 JOIN 解码(COALESCE(dict_desc, raw_code))。
A72: 数据粒度：1 行/(field_name, code)。
A73: 上游链路：Servicer(Newrez) 文件(L0) → newrez.portnewrezdatadic
A74: 全部上游表：Servicer 文件(S3, L0)
A75: 下游链路：⋈ basic_data_pool_config.py(LM :835-840 / BK :367) → port.basic_data_loan_foreclosure_loss_mitigation / _bankruptcy(解码列) → bpms.sync_loan_foreclosure_loss_mitigation / _bankruptcy → 视图 → BPS
A76: 全部下游表：port.basic_data_loan_foreclosure_loss_mitigation、port.basic_data_loan_foreclosure_bankruptcy、bpms.sync_loan_foreclosure_loss_mitigation、bpms.sync_loan_foreclosure_bankruptcy
A77: ▲ 以上为「业务含义与全链路血缘」说明块；下方为原始数据 ────
A78: 编码 | B78: 解码（description） | C78: 模块
A79: 1 | B79: Received | C79: Bankruptcy
A80: 4 | B80: Confirmation | C80: Bankruptcy
A81: 8 | B81: Discharged | C81: Bankruptcy
A82: 13 | B82: Transfer of Claim | C82: Bankruptcy
A83: 17 | B83: Termination | C83: Bankruptcy
A84: 21 | B84: Motion to Determine Final Cure | C84: Bankruptcy
